Workbook

Sheet COT
F1: Calle seis Mz. D lote 13
F2: Urb. Industrial Grimaneza, Callao
F3: postmaster@bbti.com.pe
F4: www.bbti.com.pe
B6: BBTI S.A.C | D6: FABRICANTES DE TABLEROS ELECTRICOS | E6: CALIDAD Y GARANTIA
B7: 20565747356
F9: Callao, 13 de marzo del 2026
B11: COTIZACION: BB - 046- 25 Rev.2
B13: Sres | C13: : | D13: CONSORIO FOTOVOLTAICO ANDOAS
B14: R.U.C. | C14: : | D14: 20510413301
B15: Atencion | C15: : | D15: HENRY LOZANO
B16: Ref | C16: : | D16: 946-928-450
B17: Asunto | C17: : | D17: COTIZACION DE TABLEROS ELECTRICOS PARA LA OBRA: “AMPLIACIÓN DE LA ELECTRIFICACIÓN RURAL EN EL DISTRITO DE ANDOAS, PROVINCIA DATEM DEL MARAÑÓN, REGIÓN LORETO”
B19: Estimados Sres:
B20: En atencion a su grata solicitud, tenemos a bien alcanzarles nuestra propuesta tecnico economica
B22: ITEM | C22: CANT. | D22: DESCRIPCIÓN | E22: P. UNITARIO | F22: P. TOTAL | G22: ESPECIFICACION
E23: S/ | F23: S/ | G23: TECNICA
B24: 1 | D24: CAJAS DE TRANSICION CON ESTRUCTURA DE SOPORTE
B25: =+B24+0.01 -> 1.01 | C25: 8 | D25: CAJA CON SOPORTE 01 STRING 1KV | E25: =+E169 -> 8840.0856 | F25: =ROUND(E25*C25,2) -> 70720.68 | G25: ETS-SFVC - 12
B26: =+B25+0.01 -> 1.02 | C26: 3 | D26: CAJA CON SOPORTE 02 STRING 1KV | E26: =+E185 -> 16892.448 | F26: =ROUND(E26*C26,2) -> 50677.34 | G26: ETS-SFVC - 12
B27: =+B26+0.01 -> 1.03 | C27: 5 | D27: CAJA CON SOPORTE 03 STRING 1KV | E27: =+E201 -> 24944.811 | F27: =ROUND(E27*C27,2) -> 124724.05 | G27: ETS-SFVC - 12
B28: =+B27+0.01 -> 1.04 | C28: 23 | D28: CAJA CON SOPORTE 04 STRING 1KV | E28: =+E217 -> 32997.173 | F28: =ROUND(E28*C28,2) -> 758934.98 | G28: ETS-SFVC - 12
B29: =+B28+0.01 -> 1.05 | C29: 8 | D29: CAJA CON SOPORTE 05 STRING 1KV | E29: =+E233 -> 41059.286 | F29: =ROUND(E29*C29,2) -> 328474.28 | G29: ETS-SFVC - 12
B30: =+B29+0.01 -> 1.06 | C30: 5 | D30: CAJA CON SOPORTE 06 STRING 1KV | E30: =+E249 -> 49111.648 | F30: =ROUND(E30*C30,2) -> 245558.24 | G30: ETS-SFVC - 12
B31: =+B30+0.01 -> 1.07 | C31: 3 | D31: CAJA CON SOPORTE 07 STRING 1KV | E31: =+E265 -> 57164.011 | F31: =ROUND(E31*C31,2) -> 171492.03 | G31: ETS-SFVC - 12
B32: 2 | D32: CAJAS DE PARALELAJE CON ESTRUCTURA DE SOPORTE
B33: =+B32+0.01 -> 2.01 | C33: 1 | D33: CAJA PARA ENTRADA DE 04 STRING 1KV EN PARALELAJE PARA SALIDA DE 02 STRINGS 1KV | E33: =ROUND(E282,2) -> 28502.75 | F33: =ROUND(E33*C33,2) -> 28502.75 | G33: ETS-SFVC - 12
B34: =+B33+0.01 -> 2.02 | C34: 1 | D34: CAJA PARA ENTRADA DE 06 STRING 1KV EN PARALELAJE PARA SALIDA DE 02 STRINGS 1KV | E34: =ROUND(E299,2) -> 36542.27 | F34: =ROUND(E34*C34,2) -> 36542.27 | G34: ETS-SFVC - 12
B35: 3 | D35: TABLEROS DE INTERCONEXION DE POTENCIA (GABINETES ELECTRICOS HERMETICO, DE CONTROL PARA LOS INVERSORES)
B36: =+B35+0.01 -> 3.01 | C36: 4 | D36: TABLEROS DE POTENCIA TIPO 01 (incluye aire acondicionado) | E36: =ROUND(E316,2) -> 1225.2 | F36: =ROUND(E36*C36,2) -> 4900.8 | G36: ETS-SFVC - 19
B37: =+B36+0.01 -> 3.02 | C37: 2 | D37: TABLEROS DE POTENCIA TIPO 02 (incluye aire acondicionado) | E37: =ROUND(E345,2) -> 1215.6 | F37: =ROUND(E37*C37,2) -> 2431.2 | G37: ETS-SFVC - 19
B38: =+B37+0.01 -> 3.03 | C38: 1 | D38: TABLEROS DE POTENCIA TIPO 03 (incluye aire acondicionado) | E38: =ROUND(E372,2) -> 1210.8 | F38: =ROUND(E38*C38,2) -> 1210.8 | G38: ETS-SFVC - 19
B39: =+B38+0.01 -> 3.04 | C39: 1 | D39: TABLEROS DE POTENCIA TIPO 04 (incluye aire acondicionado) | E39: =ROUND(E399,2) -> 1220.4 | F39: =ROUND(E39*C39,2) -> 1220.4 | G39: ETS-SFVC - 19
B40: =+B39+0.01 -> 3.05 | C40: 2 | D40: TABLEROS DE POTENCIA TIPO 05 (incluye aire acondicionado) | E40: =ROUND(E426,2) -> 2125.2 | F40: =ROUND(E40*C40,2) -> 4250.4 | G40: ETS-SFVC - 19
B41: =+B40+0.01 -> 3.06 | C41: 3 | D41: TABLEROS DE POTENCIA TIPO 06 (incluye aire acondicionado) | E41: =ROUND(E453,2) -> 1337.3 | F41: =ROUND(E41*C41,2) -> 4011.9 | G41: ETS-SFVC - 19
B42: =+B41+0.01 -> 3.07 | C42: 3 | D42: TABLEROS DE POTENCIA TIPO 07 (incluye aire acondicionado) | E42: =ROUND(E477,2) -> 2576.26 | F42: =ROUND(E42*C42,2) -> 7728.78 | G42: ETS-SFVC - 19
B43: =+B42+0.01 -> 3.08 | C43: 1 | D43: TABLEROS DE POTENCIA TIPO 08 (incluye aire acondicionado) | E43: =ROUND(E502,2) -> 2146.8 | F43: =ROUND(E43*C43,2) -> 2146.8 | G43: ETS-SFVC - 19
B44: =+B43+0.01 -> 3.09 | C44: 3 | D44: TABLEROS DE POTENCIA TIPO 09 (incluye aire acondicionado) | E44: =ROUND(E530,2) -> 3139.2 | F44: =ROUND(E44*C44,2) -> 9417.6 | G44: ETS-SFVC - 19
B45: =+B44+0.01 -> 3.1 | C45: 1 | D45: TABLEROS DE POTENCIA TIPO 09.1 (incluye aire acondicionado) | E45: =+E530 -> 3139.2 | F45: =ROUND(E45*C45,2) -> 3139.2 | G45: ETS-SFVC - 19
B46: =+B45+0.01 -> 3.11 | C46: 2 | D46: TABLEROS DE POTENCIA TIPO 10 (incluye aire acondicionado) | E46: =ROUND(E587,2) -> 4165.2 | F46: =ROUND(E46*C46,2) -> 8330.4 | G46: ETS-SFVC - 19
B47: =+B46+0.01 -> 3.12 | C47: 2 | D47: TABLEROS DE POTENCIA TIPO 10.1 (incluye aire acondicionado) | E47: =ROUND(E615,2) -> 4165.2 | F47: =ROUND(E47*C47,2) -> 8330.4 | G47: ETS-SFVC - 19
B48: =+B47+0.01 -> 3.13 | C48: 3 | D48: TABLEROS DE POTENCIA TIPO 11 (incluye aire acondicionado) | E48: =ROUND(E642,2) -> 5110.8 | F48: =ROUND(E48*C48,2) -> 15332.4 | G48: ETS-SFVC - 19
B49: =+B48+0.01 -> 3.14 | C49: 1 | D49: TABLEROS DE POTENCIA TIPO 12 (incluye aire acondicionado) | E49: =ROUND(E670,2) -> 5110.8 | F49: =ROUND(E49*C49,2) -> 5110.8 | G49: ETS-SFVC - 19
B50: =+B49+0.01 -> 3.15 | C50: 4 | D50: TABLEROS DE POTENCIA TIPO 12.1 (incluye aire acondicionado) | E50: =ROUND(E699,2) -> 5110.8 | F50: =ROUND(E50*C50,2) -> 20443.2 | G50: ETS-SFVC - 19
B51: =+B50+0.01 -> 3.16 | C51: 5 | D51: TABLEROS DE POTENCIA TIPO 13 (incluye aire acondicionado) | E51: =ROUND(E727,2) -> 5961.6 | F51: =ROUND(E51*C51,2) -> 29808 | G51: ETS-SFVC - 19
B52: =+B51+0.01 -> 3.17 | C52: 1 | D52: TABLEROS DE POTENCIA TIPO 14 (incluye aire acondicionado) | E52: =+E755 -> 6978 | F52: =ROUND(E52*C52,2) -> 6978 | G52: ETS-SFVC - 19
B53: =+B52+0.01 -> 3.18 | C53: 2 | D53: TABLEROS DE POTENCIA TIPO 14.1 (incluye aire acondicionado) | E53: =+E782 -> 6978 | F53: =ROUND(E53*C53,2) -> 13956 | G53: ETS-SFVC - 19
B54: =+B53+0.01 -> 3.19 | C54: 1 | D54: TABLEROS DE POTENCIA TIPO 15 (incluye aire acondicionado) | E54: =+E809 -> 3064.8 | F54: =ROUND(E54*C54,2) -> 3064.8 | G54: ETS-SFVC - 19
B55: =+B54+0.01 -> 3.2 | C55: 1 | D55: TABLEROS DE POTENCIA TIPO 14 (C1.1) (incluye aire acondicionado) | E55: =ROUND(E836,2) -> 321.6 | F55: =ROUND(E55*C55,2) -> 321.6 | G55: ETS-SFVC - 19
B56: =+B55+0.01 -> 3.21 | C56: 1 | D56: TABLEROS DE POTENCIA TIPO 14 (C1.2) (incluye aire acondicionado) | E56: =ROUND(E856,2) -> 4174.8 | F56: =ROUND(E56*C56,2) -> 4174.8 | G56: ETS-SFVC - 19
B57: =+B56+0.01 -> 3.22 | C57: 1 | D57: TABLEROS DE POTENCIA TIPO 14 (C1.3) (incluye aire acondicionado) | E57: =ROUND(E883,2) -> 321.6 | F57: =ROUND(E57*C57,2) -> 321.6 | G57: ETS-SFVC - 19
B58: =+B57+0.01 -> 3.23 | C58: 1 | D58: TABLEROS DE POTENCIA TIPO 14 (C1.4) (incluye aire acondicionado) | E58: =ROUND(E903,2) -> 4150.8 | F58: =ROUND(E58*C58,2) -> 4150.8 | G58: ETS-SFVC - 19
B59: =+B58+0.01 -> 3.24 | C59: 1 | D59: TABLEROS DE POTENCIA TIPO 14 (C2.1) (incluye aire acondicionado) | E59: =ROUND(E930,2) -> 321.6 | F59: =ROUND(E59*C59,2) -> 321.6 | G59: ETS-SFVC - 19
B60: =+B59+0.01 -> 3.25 | C60: 1 | D60: TABLEROS DE POTENCIA TIPO 14 (C2.2) (incluye aire acondicionado) | E60: =ROUND(E950,2) -> 4150.8 | F60: =ROUND(E60*C60,2) -> 4150.8 | G60: ETS-SFVC - 19
B61: =+B60+0.01 -> 3.26 | C61: 1 | D61: TABLEROS DE POTENCIA TIPO 14 (C2.3) (incluye aire acondicionado) | E61: =ROUND(E977,2) -> 321.6 | F61: =ROUND(E61*C61,2) -> 321.6 | G61: ETS-SFVC - 19
B62: =+B61+0.01 -> 3.27 | C62: 1 | D62: TABLEROS DE POTENCIA TIPO 14 (C2.4) (incluye aire acondicionado) | E62: =ROUND(E997,2) -> 4150.8 | F62: =ROUND(E62*C62,2) -> 4150.8 | G62: ETS-SFVC - 19
B63: =+B62+0.01 -> 3.28 | C63: 1 | D63: TABLEROS DE POTENCIA TIPO 14 (C3.1) (incluye aire acondicionado) | E63: =ROUND(E1024,2) -> 321.6 | F63: =ROUND(E63*C63,2) -> 321.6 | G63: ETS-SFVC - 19
B64: =+B63+0.01 -> 3.29 | C64: 1 | D64: TABLEROS DE POTENCIA TIPO 14 (C3.2) (incluye aire acondicionado) | E64: =ROUND(E1044,2) -> 4140 | F64: =ROUND(E64*C64,2) -> 4140 | G64: ETS-SFVC - 19
B65: =+B64+0.01 -> 3.3 | C65: 1 | D65: TABLEROS DE POTENCIA TIPO 14 (C3.3) (incluye aire acondicionado) | E65: =ROUND(E1071,2) -> 321.6 | F65: =ROUND(E65*C65,2) -> 321.6 | G65: ETS-SFVC - 19
B66: =+B65+0.01 -> 3.31 | C66: 1 | D66: TABLEROS DE POTENCIA TIPO 14 (C3.4) (incluye aire acondicionado) | E66: =ROUND(E1091,2) -> 4140 | F66: =ROUND(E66*C66,2) -> 4140 | G66: ETS-SFVC - 19
B67: 4 | D67: TABLEROS BUSBAR
B68: =+B67+0.01 -> 4.01 | C68: 4 | D68: TABLERO BUSBAR - TIPO 01 | E68: =+E1118 -> 562.8 | F68: =ROUND(E68*C68,2) -> 2251.2
B69: =+B68+0.01 -> 4.02 | C69: 2 | D69: TABLERO BUSBAR - TIPO 02 | E69: =+E1138 -> 860.4 | F69: =ROUND(E69*C69,2) -> 1720.8
B70: =+B69+0.01 -> 4.03 | C70: 1 | D70: TABLERO BUSBAR - TIPO 03 | E70: =+E1158 -> 548.4 | F70: =ROUND(E70*C70,2) -> 548.4
B71: =+B70+0.01 -> 4.04 | C71: 1 | D71: TABLERO BUSBAR - TIPO 04 | E71: =+E1178 -> 565.2 | F71: =ROUND(E71*C71,2) -> 565.2
B72: =+B71+0.01 -> 4.05 | C72: 2 | D72: TABLERO BUSBAR - TIPO 05 | E72: =+E1198 -> 565.2 | F72: =ROUND(E72*C72,2) -> 1130.4
B73: =+B72+0.01 -> 4.06 | C73: 3 | D73: TABLERO BUSBAR - TIPO 06 | E73: =+E1218 -> 1478.4 | F73: =ROUND(E73*C73,2) -> 4435.2
B74: =+B73+0.01 -> 4.07 | C74: 3 | D74: TABLERO BUSBAR - TIPO 07 | E74: =+E1239 -> 1784.4 | F74: =ROUND(E74*C74,2) -> 5353.2
B75: =+B74+0.01 -> 4.08 | C75: 1 | D75: TABLERO BUSBAR - TIPO 08 | E75: =+E1260 -> 626.4 | F75: =ROUND(E75*C75,2) -> 626.4
B76: =+B75+0.01 -> 4.09 | C76: 3 | D76: TABLERO BUSBAR - TIPO 09 | E76: =+E1280 -> 1089.6 | F76: =ROUND(E76*C76,2) -> 3268.8
B77: =+B76+0.01 -> 4.1 | C77: 1 | D77: TABLERO BUSBAR - TIPO 09.1 | E77: =+E1300 -> 1089.6 | F77: =ROUND(E77*C77,2) -> 1089.6
B78: =+B77+0.01 -> 4.11 | C78: 2 | D78: TABLERO BUSBAR - TIPO 10 | E78: =+E1320 -> 1914 | F78: =ROUND(E78*C78,2) -> 3828
B79: =+B78+0.01 -> 4.12 | C79: 2 | D79: TABLERO BUSBAR - TIPO 10.1 | E79: =+E1340 -> 1564.8 | F79: =ROUND(E79*C79,2) -> 3129.6
B80: =+B79+0.01 -> 4.13 | C80: 3 | D80: TABLERO BUSBAR - TIPO 11 | E80: =+E1360 -> 2028 | F80: =ROUND(E80*C80,2) -> 6084
B81: =+B80+0.01 -> 4.14 | C81: 1 | D81: TABLERO BUSBAR - TIPO 12 | E81: =+E1380 -> 2028 | F81: =ROUND(E81*C81,2) -> 2028
B82: =+B81+0.01 -> 4.15 | C82: 4 | D82: TABLERO BUSBAR - TIPO 12.1 | E82: =+E1400 -> 2028 | F82: =ROUND(E82*C82,2) -> 8112
B83: =+B82+0.01 -> 4.16 | C83: 5 | D83: TABLERO BUSBAR - TIPO 13 | E83: =+E1420 -> 1812 | F83: =ROUND(E83*C83,2) -> 9060
B84: =+B83+0.01 -> 4.17 | C84: 1 | D84: TABLERO BUSBAR - TIPO 14 | E84: =+E1440 -> 2286 | F84: =ROUND(E84*C84,2) -> 2286
B85: =+B84+0.01 -> 4.18 | C85: 2 | D85: TABLERO BUSBAR - TIPO 14.1 | E85: =+E1460 -> 2286 | F85: =ROUND(E85*C85,2) -> 4572
B86: =+B85+0.01 -> 4.19 | C86: 1 | D86: TABLERO BUSBAR - TIPO 15 | E86: =+E1480 -> 2098.8 | F86: =ROUND(E86*C86,2) -> 2098.8
B87: =+B86+0.01 -> 4.2 | C87: 1 | D87: TABLERO BUSBAR - TIPO 14 (C1.1) | E87: =+E1500 -> 2037.6 | F87: =ROUND(E87*C87,2) -> 2037.6
B88: =+B87+0.01 -> 4.21 | C88: 1 | D88: TABLERO BUSBAR - TIPO 14 (C1.2) | E88: =+E1519 -> 2610 | F88: =ROUND(E88*C88,2) -> 2610
B89: =+B88+0.01 -> 4.22 | C89: 1 | D89: TABLERO BUSBAR - TIPO 14 (C1.3) | E89: =+E1539 -> 2037.6 | F89: =ROUND(E89*C89,2) -> 2037.6
B90: =+B89+0.01 -> 4.23 | C90: 1 | D90: TABLERO BUSBAR - TIPO 14 (C1.4) | E90: =+E1558 -> 2610 | F90: =ROUND(E90*C90,2) -> 2610
B91: =+B90+0.01 -> 4.24 | C91: 1 | D91: TABLERO BUSBAR - TIPO 14 (C2.1) | E91: =+E1578 -> 2037.6 | F91: =ROUND(E91*C91,2) -> 2037.6
B92: =+B91+0.01 -> 4.25 | C92: 1 | D92: TABLERO BUSBAR - TIPO 14 (C2.2) | E92: =+E1597 -> 2610 | F92: =ROUND(E92*C92,2) -> 2610
B93: =+B92+0.01 -> 4.26 | C93: 1 | D93: TABLERO BUSBAR - TIPO 14 (C2.3) | E93: =+E1617 -> 2037.6 | F93: =ROUND(E93*C93,2) -> 2037.6
B94: =+B93+0.01 -> 4.27 | C94: 1 | D94: TABLERO BUSBAR - TIPO 14 (C2.4) | E94: =+E1636 -> 2610 | F94: =ROUND(E94*C94,2) -> 2610
B95: =+B94+0.01 -> 4.28 | C95: 1 | D95: TABLERO BUSBAR - TIPO 14 (C3.1) | E95: =+E1656 -> 2058 | F95: =ROUND(E95*C95,2) -> 2058
B96: =+B95+0.01 -> 4.29 | C96: 1 | D96: TABLERO BUSBAR - TIPO 14 (C3.2) | E96: =+E1675 -> 2630.4 | F96: =ROUND(E96*C96,2) -> 2630.4
B97: =+B96+0.01 -> 4.3 | C97: 1 | D97: TABLERO BUSBAR - TIPO 14 (C3.3) | E97: =+E1695 -> 2058 | F97: =ROUND(E97*C97,2) -> 2058
B98: =+B97+0.01 -> 4.31 | C98: 1 | D98: TABLERO BUSBAR - TIPO 14 (C3.4) | E98: =+E1714 -> 2630.4 | F98: =ROUND(E98*C98,2) -> 2630.4
B99: 5 | D99: TABLERO FOTOVOLTAICO AC AUTOSOPORTADO
B100: =+B99+0.01 -> 5.01 | C100: 1 | D100: TABLERO FOTOVOLTAICO AC AUTOSOPORTARDO EXTERIOR DE BARRAS R,S,T,N DE 380VAC 500A (CONEXIONADO DE INVERSORES AISLADOS Y DE RED) | E100: =ROUND(E1734,2) -> 340.8 | F100: =ROUND(E100*C100,2) -> 340.8
B101: 6 | D101: TABLERO FOTOVOLTAICO AC CON ITM PARA INVERSORES.
B102: =+B101+0.01 -> 6.01 | C102: 4 | D102: TABLERO TFV-AC - TIPO 01 | E102: =+E1756 -> 1314 | F102: =ROUND(E102*C102,2) -> 5256
B103: =+B102+0.01 -> 6.02 | C103: 2 | D103: TABLERO TFV-AC - TIPO 02 | E103: =+E1781 -> 1314 | F103: =ROUND(E103*C103,2) -> 2628
B104: =+B103+0.01 -> 6.03 | C104: 1 | D104: TABLERO TFV-AC - TIPO 03 | E104: =+E1806 -> 1314 | F104: =ROUND(E104*C104,2) -> 1314
B105: =+B104+0.01 -> 6.04 | C105: 1 | D105: TABLERO TFV-AC - TIPO 04 | E105: =+E1831 -> 1314 | F105: =ROUND(E105*C105,2) -> 1314
B106: =+B105+0.01 -> 6.05 | C106: 2 | D106: TABLERO TFV-AC - TIPO 05 | E106: =+E1856 -> 1314 | F106: =ROUND(E106*C106,2) -> 2628
...

Sheet Precios Equipos
B2: RESUMEN DE COSTOS (EQUIPOS, BARRAS, GABINETE, M. OBRA)
F4: T. Cambio | G4: 3.4
F5: Incremento ABB | G5: 1.13
F6: Dscto. ABB | G6: 0.52
E7: AIRE ACONDICIONADO | F7: Desaduanaje | G7: 1.5
F8: Aumento | G8: 2
B10: ITEM | C10: DESCRIPCION (EQUIPOS) | D10: CODIGO | E10: UND | F10: P.UNIT | G10: P.TOTAL
C11: INTERRUPTORES CAJA MOLDEADA CORRIENTE ALTERNA
B12: 1 | C12: ITM 2x16A, Caja Moldeada, 50kA en 220VAC, A1N, ABB | E12: =SUMIFS(COT!$Q$168:$Q$2789,COT!$D$168:$D$2789,'Precios Equipos'!C12) -> 20 | F12: 117 | G12: =+F12*E12 -> 2340 | N12: =+K12-E12 -> -20
B13: =+B12+1 -> 2 | C13: ITM 2x20A, Caja Moldeada, 50kA en 220VAC, A1N, ABB | E13: =SUMIFS(COT!$Q$168:$Q$2789,COT!$D$168:$D$2789,'Precios Equipos'!C13) -> 8 | F13: 117 | G13: =+F13*E13 -> 936 | N13: =+K13-E13 -> -8
B14: =+B13+1 -> 3 | C14: ITM 2x25A, Caja Moldeada, 50kA en 220VAC, A1N, ABB | E14: =SUMIFS(COT!$Q$168:$Q$2789,COT!$D$168:$D$2789,'Precios Equipos'!C14) -> 110 | F14: 123 | G14: =+F14*E14 -> 13530 | N14: =+K14-E14 -> -110
B15: =+B14+1 -> 4 | C15: ITM 2x32A, Caja Moldeada, 50kA en 220VAC, A1N, ABB | E15: =SUMIFS(COT!$Q$168:$Q$2789,COT!$D$168:$D$2789,'Precios Equipos'!C15) -> 88 | F15: 117 | G15: =+F15*E15 -> 10296 | N15: =+K15-E15 -> -88
B16: =+B15+1 -> 5 | C16: ITM 2x50A, Caja Moldeada, 50kA en 220VAC, A1N, ABB | E16: =SUMIFS(COT!$Q$168:$Q$2789,COT!$D$168:$D$2789,'Precios Equipos'!C16) -> 36 | F16: 145 | G16: =+F16*E16 -> 5220 | N16: =+K16-E16 -> -36
B17: =+B16+1 -> 6 | C17: ITM 2x63A, Caja Moldeada, 50kA en 220VAC, A1N, ABB | E17: =SUMIFS(COT!$Q$168:$Q$2789,COT!$D$168:$D$2789,'Precios Equipos'!C17) -> 9 | F17: 159 | G17: =+F17*E17 -> 1431 | N17: =+K17-E17 -> -9
B18: =+B17+1 -> 7 | C18: ITM 2x100A, Caja Moldeada 100A, 50kA en 220VAC, A1N/P, ABB | E18: =SUMIFS(COT!$Q$168:$Q$2789,COT!$D$168:$D$2789,'Precios Equipos'!C18) -> 138 | F18: 132 | G18: =+F18*E18 -> 18216 | N18: =+K18-E18 -> -138
B19: =+B18+1 -> 8 | C19: ITM 3x25A, Caja Moldeada (17.5-25)A, 25kA en 380VAC, XT1C, ABB | E19: =SUMIFS(COT!$Q$168:$Q$2789,COT!$D$168:$D$2789,'Precios Equipos'!C19) -> 8 | F19: 246 | G19: =+F19*E19 -> 1968 | N19: =+K19-E19 -> -8
B20: =+B19+1 -> 9 | C20: ITM 3x32A, Caja Moldeada (22.4-32)A, 25kA en 380VAC, XT1C, ABB | E20: =SUMIFS(COT!$Q$168:$Q$2789,COT!$D$168:$D$2789,'Precios Equipos'!C20) -> 16 | F20: 246 | G20: =+F20*E20 -> 3936 | N20: =+K20-E20 -> -16
B21: =+B20+1 -> 10 | C21: ITM 3x50A, Caja Moldeada (35-50)A, 25kA en 380VAC, XT1C, ABB | E21: =SUMIFS(COT!$Q$168:$Q$2789,COT!$D$168:$D$2789,'Precios Equipos'!C21) -> 41 | F21: 246 | G21: =+F21*E21 -> 10086 | N21: =+K21-E21 -> -41
B22: =+B21+1 -> 11 | C22: ITM 3x80A, Caja Moldeada (56-80)A, 25kA en 380VAC, XT1C, ABB | E22: =SUMIFS(COT!$Q$168:$Q$2789,COT!$D$168:$D$2789,'Precios Equipos'!C22) -> 2 | F22: 255 | G22: =+F22*E22 -> 510 | N22: =+K22-E22 -> -2
B23: =+B22+1 -> 12 | C23: ITM 4x100A, Caja Moldeada (70-100)A, 36kA en 380VAC, XT1, ABB | E23: =SUMIFS(COT!$Q$168:$Q$2789,COT!$D$168:$D$2789,'Precios Equipos'!C23) -> 12 | F23: =1234*G5*G6*1.35 -> 978.88284 | G23: =+F23*E23 -> 11746.594 | N23: =+K23-E23 -> -12
B24: =+B23+1 -> 13 | C24: ITM 4x100A, Caja Moldeada (70-100)A, 25kA en 380VAC, XT1C, ABB | E24: =SUMIFS(COT!$Q$168:$Q$2789,COT!$D$168:$D$2789,'Precios Equipos'!C24) -> 12 | F24: 382 | G24: =+F24*E24 -> 4584 | N24: =+K24-E24 -> -12
B25: =+B24+1 -> 14 | C25: ITM 3x800A, Caja Moldeada (320-800)A, 36kA en 380VAC, XT6N, ABB | E25: =SUMIFS(COT!$Q$168:$Q$2789,COT!$D$168:$D$2789,'Precios Equipos'!C25) -> 1 | F25: 4140 | G25: =+F25*E25 -> 4140 | N25: =+K25-E25 -> -1
B26: =+B25+1 -> 15 | C26: ITM 2 x 16A, Caja Moldeada, 15KA@440V, 2B160, SIGMA ELEKTRIK | E26: =SUMIFS(COT!$Q$168:$Q$2789,COT!$D$168:$D$2789,'Precios Equipos'!C26) -> 115 | F26: 232.96 | G26: =+F26*E26 -> 26790.4 | N26: =+K26-E26 -> -115
B27: =+B26+1 -> 16 | C27: ITM 2 x 25A, Caja Moldeada, 15KA@440V, 2B160, SIGMA ELEKTRIK | E27: =SUMIFS(COT!$Q$168:$Q$2789,COT!$D$168:$D$2789,'Precios Equipos'!C27) -> 91 | F27: 232.96 | G27: =+F27*E27 -> 21199.36 | N27: =+K27-E27 -> -91
B28: =+B27+1 -> 17 | C28: ITM 2 x 40A, Caja Moldeada, 15KA@440V, 2B160, SIGMA ELEKTRIK | E28: =SUMIFS(COT!$Q$168:$Q$2789,COT!$D$168:$D$2789,'Precios Equipos'!C28) -> 61 | F28: 232.96 | G28: =+F28*E28 -> 14210.56 | N28: =+K28-E28 -> -61
B29: =+B28+1 -> 18 | C29: ITM 2 x 63A, Caja Moldeada, 15KA@440V, 2B160, SIGMA ELEKTRIK | E29: =SUMIFS(COT!$Q$168:$Q$2789,COT!$D$168:$D$2789,'Precios Equipos'!C29) -> 20 | F29: 250.64 | G29: =+F29*E29 -> 5012.8 | N29: =+K29-E29 -> -20
B30: =+B29+1 -> 19 | C30: ITM 3 x 25A, Caja Moldeada, Reg. (20-25)A, 25KA@380V, 3B160, SIGMA ELEKTRIK | E30: =SUMIFS(COT!$Q$168:$Q$2789,COT!$D$168:$D$2789,'Precios Equipos'!C30) -> 1 | F30: 190 | G30: =+F30*E30 -> 190 | N30: =+K30-E30 -> -1
B31: =+B30+1 -> 20 | C31: ITM 3 x 40A, Caja Moldeada, Reg. (32-40)A, 25KA@380V, 3B160, SIGMA ELEKTRIK | E31: =SUMIFS(COT!$Q$168:$Q$2789,COT!$D$168:$D$2789,'Precios Equipos'!C31) -> 5 | F31: 190 | G31: =+F31*E31 -> 950 | N31: =+K31-E31 -> -5
B32: =+B31+1 -> 21 | C32: ITM 3 x 63A, Caja Moldeada, Reg. (50.4-63)A, 25KA@380V, 3B160, SIGMA ELEKTRIK | E32: =SUMIFS(COT!$Q$168:$Q$2789,COT!$D$168:$D$2789,'Precios Equipos'!C32) -> 1 | F32: 190 | G32: =+F32*E32 -> 190 | N32: =+K32-E32 -> -1
C33: MEDIDORES | N33: =+K33-E33 -> 0
B34: =+B32+1 -> 22 | C34: Medidor Electronico HXE34KS-1, HEXING | E34: =SUMIFS(COT!$Q$168:$Q$2789,COT!$D$168:$D$2789,'Precios Equipos'!C34) -> 42 | F34: 190 | G34: =+F34*E34 -> 7980 | N34: =+K34-E34 -> -42
B35: =+B34+1 -> 23 | C35: Medidor Electronico Monofasico HXE12ES, HEXING | E35: =SUMIFS(COT!$Q$168:$Q$2789,COT!$D$168:$D$2789,'Precios Equipos'!C35) -> 41 | F35: 41.8 | G35: =+F35*E35 -> 1713.8 | N35: =+K35-E35 -> -41
B36: =+B35+1 -> 24 | C36: Medidor Electronico Polifasico HXF300, HEXING | E36: =SUMIFS(COT!$Q$168:$Q$2789,COT!$D$168:$D$2789,'Precios Equipos'!C36) -> 1 | F36: 1824 | G36: =+F36*E36 -> 1824 | N36: =+K36-E36 -> -1
B37: =+B36+1 -> 25 | C37: Medidor Multifuncion comunicación M1M 15 Modbus RTU ABB | E37: =SUMIFS(COT!$Q$168:$Q$2789,COT!$D$168:$D$2789,'Precios Equipos'!C37) -> 0 | F37: 662.81 | G37: =+F37*E37 -> 0 | N37: =+K37-E37 -> 0
C38: INTERRUPTORES CAJA MOLDEADA CORRIENTE CONTINUA | N38: =+K38-E38 -> 0
B39: =+B37+1 -> 26 | C39: ITM 2x40A, Caja Moldeada, 50kA en 220V, A1N, ABB, DC | E39: =SUMIFS(COT!$Q$168:$Q$2789,COT!$D$168:$D$2789,'Precios Equipos'!C39) -> 2 | F39: 123 | G39: =+F39*E39 -> 246 | N39: =+K39-E39 -> -2
B40: =+B39+1 -> 27 | C40: ITM 2x50A, Caja Moldeada, 50kA en 220V, A1N, ABB, DC | E40: =SUMIFS(COT!$Q$168:$Q$2789,COT!$D$168:$D$2789,'Precios Equipos'!C40) -> 9 | F40: 123 | G40: =+F40*E40 -> 1107 | N40: =+K40-E40 -> -9
B41: =+B40+1 -> 28 | C41: ITM 2x63A, Caja Moldeada 63A, 50kA en 220V, A1N/P, ABB, DC | E41: =SUMIFS(COT!$Q$168:$Q$2789,COT!$D$168:$D$2789,'Precios Equipos'!C41) -> 24 | F41: 132 | G41: =+F41*E41 -> 3168 | N41: =+K41-E41 -> -24
B42: =+B41+1 -> 29 | C42: ITM 2x125A, Caja Moldeada 125A, 25kA en 220V, A1N/P, ABB, DC | E42: =SUMIFS(COT!$Q$168:$Q$2789,COT!$D$168:$D$2789,'Precios Equipos'!C42) -> 78 | F42: 330 | G42: =+F42*E42 -> 25740 | N42: =+K42-E42 -> -78
B43: =+B42+1 -> 30 | C43: ITM 2x160A, Caja Moldeada 160A, 50kA en 220V, A2N 250, ABB, DC | E43: =SUMIFS(COT!$Q$168:$Q$2789,COT!$D$168:$D$2789,'Precios Equipos'!C43) -> 92 | F43: 405 | G43: =+F43*E43 -> 37260 | N43: =+K43-E43 -> -92
B44: =+B43+1 -> 31 | C44: ITM 2x175A, Caja Moldeada 175A, 36kA en 220V, A2N, ABB, DC | E44: =SUMIFS(COT!$Q$168:$Q$2789,COT!$D$168:$D$2789,'Precios Equipos'!C44) -> 48 | F44: 405 | G44: =+F44*E44 -> 19440 | N44: =+K44-E44 -> -48
B45: =+B44+1 -> 32 | C45: ITM 2x225A, Caja Moldeada 225A, 36kA en 220V, A2N, ABB, DC | E45: =SUMIFS(COT!$Q$168:$Q$2789,COT!$D$168:$D$2789,'Precios Equipos'!C45) -> 6 | F45: 432 | G45: =+F45*E45 -> 2592 | N45: =+K45-E45 -> -6
B46: =+B45+1 -> 33 | C46: ITM 3x320A, Caja Moldeada (128-320)A, 70kA en 220V, XT5N, ABB, DC | E46: =SUMIFS(COT!$Q$168:$Q$2789,COT!$D$168:$D$2789,'Precios Equipos'!C46) -> 72 | F46: 1320 | G46: =+F46*E46 -> 95040 | N46: =+K46-E46 -> -72
C47: INTERRUPTORES RIEL DIN CORRIENTE ALTERNA | N47: =+K47-E47 -> 0
B48: =+B46+1 -> 34 | C48: Interruptor Riel Din 2x04A. S200 20kA en 230V en 250VAC, ABB | E48: =SUMIFS(COT!$Q$168:$Q$2789,COT!$D$168:$D$2789,'Precios Equipos'!C48) -> 162 | F48: =136*G5*G6 -> 79.9136 | G48: =+F48*E48 -> 12946.003 | N48: =+K48-E48 -> -162
B49: =+B48+1 -> 35 | C49: Interruptor Riel Din 2x06A. S200 20kA en 230VAC | E49: =SUMIFS(COT!$Q$168:$Q$2789,COT!$D$168:$D$2789,'Precios Equipos'!C49) -> 0 | F49: =103*G5*G6 -> 60.5228 | G49: =+F49*E49 -> 0 | N49: =+K49-E49 -> 0
B50: =+B49+1 -> 36 | C50: Interruptor Riel Din 2x25A. S202 20kA en 220VAC, ABB | E50: =SUMIFS(COT!$Q$168:$Q$2789,COT!$D$168:$D$2789,'Precios Equipos'!C50) -> 263 | F50: =87*G5*G6 -> 51.1212 | G50: =+F50*E50 -> 13444.876 | N50: =+K50-E50 -> -263
B51: =+B50+1 -> 37 | C51: Interruptor Riel Din 2x10A, 6KA@400V | E51: =SUMIFS(COT!$Q$168:$Q$2789,COT!$D$168:$D$2789,'Precios Equipos'!C51) -> 42 | F51: 19 | G51: =+F51*E51 -> 798 | N51: =+K51-E51 -> -42
C52: INTERRUPTORES RIEL DIN CORRIENTE CONTINUA | N52: =+K52-E52 -> 0
B53: =+B51+1 -> 38 | C53: Interruptor Riel Din 2x80A. S200M 20kA en 230V en 250VDC,ABB | E53: =SUMIFS(COT!$Q$168:$Q$2789,COT!$D$168:$D$2789,'Precios Equipos'!C53) -> 8 | F53: =710.94 -> 710.94 | G53: =+F53*E53 -> 5687.52 | N53: =+K53-E53 -> -8
B54: =+B53+1 -> 39 | C54: Interruptor Riel Din 2x50A. S200M 20kA en 230V en 250VDC, ABB | E54: =SUMIFS(COT!$Q$168:$Q$2789,COT!$D$168:$D$2789,'Precios Equipos'!C54) -> 8 | F54: 199.21 | G54: =+F54*E54 -> 1593.68 | N54: =+K54-E54 -> -8
B55: =+B54+1 -> 40 | C55: Interruptor Riel Din 2x25A. S202M 20kA en 250VDC, ABB | E55: =SUMIFS(COT!$Q$168:$Q$2789,COT!$D$168:$D$2789,'Precios Equipos'!C55) -> 382 | F55: 158.54 | G55: =+F55*E55 -> 60562.28 | N55: =+K55-E55 -> -382
B56: =+B55+1 -> 41 | C56: Interruptor Riel Din 2x32A. S202M 20kA en 250VDC, ABB | E56: =SUMIFS(COT!$Q$168:$Q$2789,COT!$D$168:$D$2789,'Precios Equipos'!C56) -> 51 | F56: =325*G5*G6 -> 190.97 | G56: =+F56*E56 -> 9739.47 | N56: =+K56-E56 -> -51
C57: INTERRUPTORES DIFERENCIALES | N57: =+K57-E57 -> 0
B58: =+B56+1 -> 42 | C58: Interruptores Diferenciales 2x25A, 30mA, Tipo AC, F200, ABB | E58: =SUMIFS(COT!$Q$168:$Q$2789,COT!$D$168:$D$2789,'Precios Equipos'!C58) -> 213 | F58: =145*G5*G6 -> 85.202 | G58: =+F58*E58 -> 18148.026 | N58: =+K58-E58 -> -213
C59: PROTECTOR DE SOBRETENSIONES Y OTROS | N59: =+K59-E59 -> 0
B60: =+B58+1 -> 43 | C60: Protector de sobretension SPD DC 2P, 1000V DC, CLAMPER/DC SURGE PROTECCION | E60: =SUMIFS(COT!$Q$168:$Q$2789,COT!$D$168:$D$2789,'Precios Equipos'!C60) -> 405 | F60: =45*3.8*1.5 -> 256.5 | G60: =+F60*E60 -> 103882.5 | N60: =+K60-E60 -> -405
B61: =+B60+1 -> 44 | C61: Protector de sobretension SPD AC 2P, 1000V AC, CLAMPER/DC SURGE PROTECCION | E61: =SUMIFS(COT!$Q$168:$Q$2789,COT!$D$168:$D$2789,'Precios Equipos'!C61) -> 59 | F61: =45*3.8*1.5 -> 256.5 | G61: =+F61*E61 -> 15133.5 | N61: =+K61-E61 -> -59
B62: =+B61+1 -> 45 | C62: Protector de sobretension SPD AC 3P+N, 230/400V, 1.5kV, 40kA, OVR, 2CTB803973R1100, ABB | E62: =SUMIFS(COT!$Q$168:$Q$2789,COT!$D$168:$D$2789,'Precios Equipos'!C62) -> 0 | F62: 530.02 | G62: =+F62*E62 -> 0 | N62: =+K62-E62 -> 0
B63: =+B62+1 -> 46 | C63: Protector de sobretension SPD AC 3P+N, 230/400V, 1.5kV, 40kA | E63: =SUMIFS(COT!$Q$168:$Q$2789,COT!$D$168:$D$2789,'Precios Equipos'!C63) -> 38 | F63: 256.5 | G63: =+F63*E63 -> 9747 | N63: =+K63-E63 -> -38
B64: =+B63+1 -> 47 | C64: Seccionador Portafusible XLP1-1P-2BC, 250A, 1SEP600116R0002, ABB | E64: =SUMIFS(COT!$Q$168:$Q$2789,COT!$D$168:$D$2789,'Precios Equipos'!C64) -> 148 | F64: 212 | G64: =+F64*E64 -> 31376 | N64: =+K64-E64 -> -148
B65: =+B64+1 -> 48 | C65: Fusible tipo NH1 250A | E65: =SUMIFS(COT!$Q$168:$Q$2789,COT!$D$168:$D$2789,'Precios Equipos'!C65) -> 145 | F65: 79.65 | G65: =+F65*E65 -> 11549.25 | N65: =+K65-E65 -> -145
B66: =+B65+1 -> 49 | C66: Base PortaFusible y Fusible 25A / 2A | E66: =SUMIFS(COT!$Q$168:$Q$2789,COT!$D$168:$D$2789,'Precios Equipos'!C66) -> 127 | F66: 10 | G66: =+F66*E66 -> 1270 | N66: =+K66-E66 -> -127
B67: =+B66+1 -> 50 | C67: Bornera 4mm2, Riel Din, tipo tornillo, ONKA | E67: =SUMIFS(COT!$Q$168:$Q$2789,COT!$D$168:$D$2789,'Precios Equipos'!C67) -> 880 | F67: 1.5 | G67: =+F67*E67 -> 1320 | N67: =+K67-E67 -> -880
B68: =+B67+1 -> 51 | C68: Conector MC4 | E68: =SUMIFS(COT!$Q$168:$Q$2789,COT!$D$168:$D$2789,'Precios Equipos'!C68) -> 440 | F68: 6.5 | G68: =+F68*E68 -> 2860 | N68: =+K68-E68 -> -440
B69: =+B68+1 -> 52 | C69: Rejilla de ventilacion 152x152 | E69: =SUMIFS(COT!$Q$168:$Q$2789,COT!$D$168:$D$2789,'Precios Equipos'!C69) -> 34 | F69: 13.466102 | G69: =+F69*E69 -> 457.84746 | N69: =+K69-E69 -> -34
B70: =+B69+1 -> 53 | C70: Contactor Trifásico 18 A, AC3, 220V, AF16, ABB | E70: =SUMIFS(COT!$Q$168:$Q$2789,COT!$D$168:$D$2789,'Precios Equipos'!C70) -> 42 | F70: 122.41 | G70: =+F70*E70 -> 5141.22 | N70: =+K70-E70 -> -42
B71: =+B70+1 -> 54 | C71: Lampara Incandescente 100 W, 220 V con Socket | E71: =SUMIFS(COT!$Q$168:$Q$2789,COT!$D$168:$D$2789,'Precios Equipos'!C71) -> 42 | F71: 3 | G71: =+F71*E71 -> 126 | N71: =+K71-E71 -> -42
B72: =+B71+1 -> 55 | C72: Transformador de corriente, 100 / 5 A, CL 0.5 | E72: =SUMIFS(COT!$Q$168:$Q$2789,COT!$D$168:$D$2789,'Precios Equipos'!C72) -> 3 | F72: 49.4 | G72: =+F72*E72 -> 148.2 | N72: =+K72-E72 -> -3
B73: =+B72+1 -> 56 | C73: Soporte de elevacion para Gabinete Metalico | E73: =SUMIFS(COT!$Q$168:$Q$2789,COT!$D$168:$D$2789,'Precios Equipos'!C73) -> 17 | F73: 50 | G73: =+F73*E73 -> 850 | N73: =+K73-E73 -> -17
... B77: =+B76+1 -> 60 | C77: Interruptor Horario Digital, Res. 3 años, 220V, 60Hz | E77: =SUMIFS(COT!$Q$168:$Q$2789,COT!$D$168:$D$2789,'Precios Equipos'!C77) -> 42 | F77: 60 | G77: =+F77*E77 -> 2520 | N77: =+K77-E77 -> -42
B78: =+B77+1 -> 61 | C78: Sistema de transferencia MXZM-63H/3B 50A | E78: =SUMIFS(COT!$Q$168:$Q$2789,COT!$D$168:$D$2789,'Precios Equipos'!C78) -> 0 | F78: =689.47+150 -> 839.47 | G78: =+F78*E78 -> 0 | N78: =+K78-E78 -> 0
B79: =+B78+1 -> 62 | C79: Sistema de transferencia NXZM-125S/3B, 25KA/380V, 80A | E79: =SUMIFS(COT!$Q$168:$Q$2789,COT!$D$168:$D$2789,'Precios Equipos'!C79) -> 0 | F79: =691.89+150 -> 841.89 | G79: =+F79*E79 -> 0 | N79: =+K79-E79 -> 0
B80: =+B79+1 -> 63 | C80: ITM 3x25A, Caja Moldeada (17.5-25)A, 36kA en 380VAC, XT1N, ABB | E80: =SUMIFS(COT!$Q$168:$Q$2789,COT!$D$168:$D$2789,'Precios Equipos'!C80) -> 0 | F80: 369.9 | G80: =+F80*E80 -> 0 | N80: =+K80-E80 -> 0
B81: =+B80+1 -> 64 | C81: Rejilla Con Filtro Para Tablero 106 X 106Mm Ral7035, JK6620, JASON FAN | E81: =SUMIFS(COT!$Q$168:$Q$2789,COT!$D$168:$D$2789,'Precios Equipos'!C81) -> 0 | F81: 11.32 | G81: =+F81*E81 -> 0 | N81: =+K81-E81 -> 0
B82: =+B81+1 -> 65 | C82: Ventilador C/ Rejilla Y Filtro Para Tablero 26M3/H 106 X 106Mm Ral7035, FJK6620PB230 , JASON FAN | E82: =SUMIFS(COT!$Q$168:$Q$2789,COT!$D$168:$D$2789,'Precios Equipos'!C82) -> 0 | F82: 43.2 | G82: =+F82*E82 -> 0 | N82: =+K82-E82 -> 0
B83: =+B82+1 -> 66 | C83: Interruptor termomagnetico 3P NXM-63S 25A (FIJO) 415V: 25KA | E83: =SUMIFS(COT!$Q$168:$Q$2789,COT!$D$168:$D$2789,'Precios Equipos'!C83) -> 0 | F83: =149.93+20 -> 169.93 | G83: =+F83*E83 -> 0 | N83: =+K83-E83 -> 0
B84: =+B83+1 -> 67 | C84: Interruptor termomagnetico 3P NXM-63S 32A (FIJO) 415V: 25KA | E84: =SUMIFS(COT!$Q$168:$Q$2789,COT!$D$168:$D$2789,'Precios Equipos'!C84) -> 0 | F84: =149.93+20 -> 169.93 | G84: =+F84*E84 -> 0 | N84: =+K84-E84 -> 0
B85: =+B84+1 -> 68 | C85: Interruptor termomagnetico 3P NXM-63S 50A (FIJO) 415V: 25KA | E85: =SUMIFS(COT!$Q$168:$Q$2789,COT!$D$168:$D$2789,'Precios Equipos'!C85) -> 0 | F85: =149.93+20 -> 169.93 | G85: =+F85*E85 -> 0 | N85: =+K85-E85 -> 0
B86: =+B85+1 -> 69 | C86: Interruptor termomagnetico 3P NXM-125S 80A (FIJO) 25KA - 380/400/415v | E86: =SUMIFS(COT!$Q$168:$Q$2789,COT!$D$168:$D$2789,'Precios Equipos'!C86) -> 0 | F86: =166.13+20 -> 186.13 | G86: =+F86*E86 -> 0 | N86: =+K86-E86 -> 0
C87: EQUIPAMIENTO SUMINISTRADO POR CLIENTE | N87: =+K87-E87 -> 0
B88: =+B86+1 -> 70 | C88: Centro de Control y Monitoreo de Microgridador de carga 450V/100A | E88: =SUMIFS(COT!$Q$168:$Q$2789,COT!$D$168:$D$2789,'Precios Equipos'!C88) -> 24 | F88: 0 | G88: =+F88*E88 -> 0 | N88: =+K88-E88 -> -24
B89: =+B88+1 -> 71 | C89: Centro de Control y Monitoreo de Microgridador de carga 450V/200A | E89: =SUMIFS(COT!$Q$168:$Q$2789,COT!$D$168:$D$2789,'Precios Equipos'!C89) -> 34 | F89: 0 | G89: =+F89*E89 -> 0 | N89: =+K89-E89 -> -34
B90: =+B89+1 -> 72 | C90: Aire Acondicionado 100W | E90: =SUMIFS(COT!$Q$168:$Q$2789,COT!$D$168:$D$2789,'Precios Equipos'!C90) -> 0 | F90: =195*G7*G8*G4 -> 1989 | G90: =+F90*E90 -> 0 | N90: =+K90-E90 -> 0
B91: =+B90+1 -> 73 | C91: Aire Acondicionado 300W | E91: =SUMIFS(COT!$Q$168:$Q$2789,COT!$D$168:$D$2789,'Precios Equipos'!C91) -> 26 | F91: =210*G7*G8*G4 -> 2142 | G91: =+F91*E91 -> 55692 | N91: =+K91-E91 -> -26
B92: =+B91+1 -> 74 | C92: Aire Acondicionado 500W | E92: =SUMIFS(COT!$Q$168:$Q$2789,COT!$D$168:$D$2789,'Precios Equipos'!C92) -> 16 | F92: =245*G7*G8*G4 -> 2499 | G92: =+F92*E92 -> 39984 | N92: =+K92-E92 -> -16
B93: =+B92+1 -> 75 | C93: Aire Acondicionado 800W | E93: =SUMIFS(COT!$Q$168:$Q$2789,COT!$D$168:$D$2789,'Precios Equipos'!C93) -> 24 | F93: =300*G7*G8*G4 -> 3060 | G93: =+F93*E93 -> 73440 | N93: =+K93-E93 -> -24
B94: =+B93+1 -> 76 | C94: Aire Acondicionado 1000W | E94: =SUMIFS(COT!$Q$168:$Q$2789,COT!$D$168:$D$2789,'Precios Equipos'!C94) -> 12 | F94: =380*G7*G8*G4 -> 3876 | G94: =+F94*E94 -> 46512 | N94: =+K94-E94 -> -12
B95: =+B94+1 -> 77 | C95: Aire Acondicionado 1250W | E95: =SUMIFS(COT!$Q$168:$Q$2789,COT!$D$168:$D$2789,'Precios Equipos'!C95) -> 30 | F95: =420*G7*G8*G4 -> 4284 | G95: =+F95*E95 -> 128520 | N95: =+K95-E95 -> -30
B96: =+B95+1 -> 78 | C96: Inversor Bidireccional 0.8 KVA | E96: =SUMIFS(COT!$Q$168:$Q$2789,COT!$D$168:$D$2789,'Precios Equipos'!C96) -> 8 | F96: 0 | G96: =+F96*E96 -> 0 | N96: =+K96-E96 -> -8
B97: =+B96+1 -> 79 | C97: Inversor Bidireccional 1.2 KVA | E97: =SUMIFS(COT!$Q$168:$Q$2789,COT!$D$168:$D$2789,'Precios Equipos'!C97) -> 4 | F97: 0 | G97: =+F97*E97 -> 0 | N97: =+K97-E97 -> -4
B98: =+B97+1 -> 80 | C98: Inversor Bidireccional 1.5 KVA | E98: =SUMIFS(COT!$Q$168:$Q$2789,COT!$D$168:$D$2789,'Precios Equipos'!C98) -> 2 | F98: 0 | G98: =+F98*E98 -> 0 | N98: =+K98-E98 -> -2
B99: =+B98+1 -> 81 | C99: Inversor Bidireccional 2 KVA | E99: =SUMIFS(COT!$Q$168:$Q$2789,COT!$D$168:$D$2789,'Precios Equipos'!C99) -> 6 | F99: 0 | G99: =+F99*E99 -> 0 | N99: =+K99-E99 -> -6
B100: =+B99+1 -> 82 | C100: Inversor Bidireccional 3 KVA | E100: =SUMIFS(COT!$Q$168:$Q$2789,COT!$D$168:$D$2789,'Precios Equipos'!C100) -> 21 | F100: 0 | G100: =+F100*E100 -> 0 | N100: =+K100-E100 -> -21
B101: =+B100+1 -> 83 | C101: Inversor Bidireccional 5 KVA | E101: =SUMIFS(COT!$Q$168:$Q$2789,COT!$D$168:$D$2789,'Precios Equipos'!C101) -> 42 | F101: 0 | G101: =+F101*E101 -> 0 | N101: =+K101-E101 -> -42
B102: =+B101+1 -> 84 | C102: Inversor Bidireccional 8 KVA | E102: =SUMIFS(COT!$Q$168:$Q$2789,COT!$D$168:$D$2789,'Precios Equipos'!C102) -> 24 | F102: 0 | G102: =+F102*E102 -> 0 | N102: =+K102-E102 -> -24
B103: =+B102+1 -> 85 | C103: Inversor Bidireccional 10 KVA | E103: =SUMIFS(COT!$Q$168:$Q$2789,COT!$D$168:$D$2789,'Precios Equipos'!C103) -> 3 | F103: 0 | G103: =+F103*E103 -> 0 | N103: =+K103-E103 -> -3
B104: =+B103+1 -> 86 | C104: Inversor Bidireccional 15 KVA | E104: =SUMIFS(COT!$Q$168:$Q$2789,COT!$D$168:$D$2789,'Precios Equipos'!C104) -> 36 | F104: 0 | G104: =+F104*E104 -> 0 | N104: =+K104-E104 -> -36
E105: SUB TOTAL | G105: =SUM(G25:G104) -> 923702.29
E106: I.G.V. | G106: =G105*0.18 -> 166266.41
...

Sheet Materiales
B2: COSTO DE MANO DE OBRA
C4: ITEM | D4: MANO DE OBRA ELECTRICIDAD INTERRUPTORES | E4: PRECIO (S/) | F4: CANTIDAD | G4: SUB TOTAL
B5: ELECTRICIDAD ITM | C5: 1 | D5: Mano de obra 6-10 polos (3-5 ITM) | E5: =70*0.75 -> 52.5 | F5: ='Precios Equipos'!E140 -> 17 | G5: =F5*E5 -> 892.5
C6: 2 | D6: Mano de obra 12-16 polos (6-8 ITM) | E6: =100*0.75 -> 75 | F6: ='Precios Equipos'!E141 -> 16 | G6: =F6*E6 -> 1200
C7: 3 | D7: Mano de obra 18-22 polos (9-11 ITM) | E7: =120*0.75 -> 90 | F7: 0 | G7: =F7*E7 -> 0
C8: 4 | D8: Mano de obra 24-28 polos (12-16 ITM) | E8: =140*0.75 -> 105 | F8: ='Precios Equipos'!#REF! -> #REF! | G8: =F8*E8 -> #REF!
C9: 5 | D9: Mano de obra 30-34 polos (18-22 ITM) | E9: =160*0.75 -> 120 | F9: ='Precios Equipos'!#REF! -> #REF! | G9: =F9*E9 -> #REF!
G10: =SUM(G5:G9) -> #REF!
C12: ITEM | D12: MANO DE OBRA ELECTRICIDAD DIFERENCIALES | E12: PRECIO (S/) | F12: CANTIDAD | G12: SUB TOTAL
C13: 6 | D13: Mano de obra 1-2 Diferenciales | E13: =20*0.75 -> 15 | F13: ='Precios Equipos'!#REF! -> #REF! | G13: =F13*E13 -> #REF!
B14: ELECTRICIDAD DIFERENCIALE | C14: 6 | D14: Mano de obra 3-5 Diferenciales | E14: =40*0.75 -> 30 | F14: ='Precios Equipos'!#REF! -> #REF! | G14: =F14*E14 -> #REF!
C15: 7 | D15: Mano de obra 6-8 Diferenciales | E15: =60*0.75 -> 45 | F15: ='Precios Equipos'!#REF! -> #REF! | G15: =F15*E15 -> #REF!
C16: 8 | D16: Mano de obra 9-11 Diferenciales | E16: =80*0.75 -> 60 | F16: 0 | G16: =F16*E16 -> 0
C17: 9 | D17: Mano de obra 12-16 Diferenciales | E17: =100*0.75 -> 75 | F17: ='Precios Equipos'!#REF! -> #REF! | G17: =F17*E17 -> #REF!
C18: 10 | D18: Mano de obra 18-22 Diferenciales | E18: =120*0.75 -> 90 | F18: ='Precios Equipos'!#REF! -> #REF! | G18: =F18*E18 -> #REF!
G19: =SUM(G14:G18) -> #REF!
C21: ITEM | D21: MANO DE OBRA ELECTRICIDAD AUTOSOPORTADO | E21: PRECIO (S/) | F21: CANTIDAD | G21: SUB TOTAL
B22: ELECTRICIDAD AUTOSOPORTADO | C22: 11 | D22: Mano de obra Autosoportado ITEM 2 | E22: 1000 | F22: 1 | G22: =F22*E22 -> 1000
C23: 11 | D23: Mano de obra Autosoportado ITEM PARA TIPO 1 AL TIPO 4.2 | E23: 1000 | F23: 1 | G23: =F23*E23 -> 1000
C24: 11 | D24: Mano de obra Autosoportado TTA-1 | E24: 1500 | F24: 1 | G24: =F24*E24 -> 1500
C25: 11 | D25: Mano de obra Autosoportado 800A | E25: 700 | F25: 1 | G25: =F25*E25 -> 700
C26: 11 | D26: Mano de obra Autosoportado TGE | E26: 1000 | F26: 1 | G26: =F26*E26 -> 1000
C27: 11 | D27: Mano de obra Autosoportado TGES.EI | E27: 350 | F27: 1 | G27: =F27*E27 -> 350
C28: 11 | D28: Mano de obra Autosoportado TBCI | E28: 350 | F28: 1 | G28: =F28*E28 -> 350
C29: 12 | D29: Mano de obra Autosoportado TGN-1 | E29: 600 | F29: 1 | G29: =F29*E29 -> 600
C30: 13 | D30: Mano de obra Autosoportado TGE-1 | E30: 500 | F30: 1 | G30: =F30*E30 -> 500
C31: 14 | D31: Mano de obra Autosoportado TGES-1 | E31: 450 | F31: 1 | G31: =F31*E31 -> 450
G32: =SUM(G22:G31) -> 7450
C35: ITEM | D35: MANO DE OBRA GABINETE EMPOTRADO | E35: PRECIO (S/) | F35: CANTIDAD | G35: SUB TOTAL
B36: EMPOTRADO | C36: 15 | D36: M. Obra Empotrado 700x450x150mm (Mecanica, Soldadura, Pintura, Armado) | E36: =40*4*0.75 -> 120 | F36: 6 | G36: =F36*E36 -> 720
C37: 16 | D37: M. Obra Empotrado 800x450x150mm (Mecanica, Soldadura, Pintura, Armado) | E37: =50*4*0.75 -> 150 | F37: 29 | G37: =F37*E37 -> 4350
C38: 16 | D38: M. Obra Empotrado 900x450x150mm (Mecanica, Soldadura, Pintura, Armado) | E38: =250*0.75 -> 187.5 | F38: 29 | G38: =F38*E38 -> 5437.5
C39: 17 | D39: M. Obra Empotrado 1000x600x150mm (Mecanica, Soldadura, Pintura, Armado) | E39: =75*4*0.75 -> 225 | F39: 19 | G39: =F39*E39 -> 4275
C40: 18 | D40: M. Obra Empotrado 1100x600x150mm (Mecanica, Soldadura, Pintura, Armado) | E40: =350*0.75 -> 262.5 | F40: 0 | G40: =F40*E40 -> 0
C41: 19 | D41: M. Obra Empotrado 1200x600x150mm (Mecanica, Soldadura, Pintura, Armado) | E41: =400*0.75 -> 300 | F41: ='Precios Equipos'!#REF! -> #REF! | G41: =F41*E41 -> #REF!
C42: 19 | D42: M. Obra Empotrado 1400x600x150mm (Mecanica, Soldadura, Pintura, Armado) | E42: =500*0.75 -> 375 | F42: ='Precios Equipos'!#REF! -> #REF! | G42: =F42*E42 -> #REF!
G43: =SUM(G36:G41) -> #REF!
C45: ITEM | D45: MANO DE OBRA GABINETE ADOSADO | E45: PRECIO (S/) | F45: CANTIDAD | G45: SUB TOTAL
B46: ADOSADO | C46: 20 | D46: M. Obra Adosado 700x450x150mm (Mecanica, Soldadura, Pintura, Armado) | E46: =40*4*0.75 -> 120 | F46: 0 | G46: =F46*E46 -> 0
C47: 21 | D47: M. Obra Adosado 800x450x150mm (Mecanica, Soldadura, Pintura, Armado) | E47: =50*4*0.75 -> 150 | F47: 0 | G47: =F47*E47 -> 0
C48: 22 | D48: M. Obra Adosado 1000x450x150mm (Mecanica, Soldadura, Pintura, Armado) | E48: =300*0.75 -> 225 | F48: 0 | G48: =F48*E48 -> 0
C49: 22 | D49: M. Obra Adosado 1000x600x150mm (Mecanica, Soldadura, Pintura, Armado) | E49: =320*0.75 -> 240 | F49: 0 | G49: =F49*E49 -> 0
C50: 23 | D50: M. Obra Adosado 1100x600x150mm (Mecanica, Soldadura, Pintura, Armado) | E50: =370*0.75 -> 277.5 | F50: 0 | G50: =F50*E50 -> 0
C51: 24 | D51: M. Obra Adosado 1200x600x150mm (Mecanica, Soldadura, Pintura, Armado) | E51: =420*0.75 -> 315 | F51: 0 | G51: =F51*E51 -> 0
C52: 24 | D52: M. Obra Adosado 1400x600x150mm (Mecanica, Soldadura, Pintura, Armado) | E52: =500*0.75 -> 375 | F52: 0 | G52: =F52*E52 -> 0
G53: =SUM(G46:G51) -> 0
C56: ITEM | D56: MANO DE OBRA GABINETE AUTOSOPORTADO | E56: PRECIO (S/) | F56: CANTIDAD | G56: SUB TOTAL
B57: AUTOSOPORTADO | C57: 25 | D57: M. Obra Autosoportado 2100x800x600mm (Mecanica, Soldadura, Pintura, Armado) | E57: 500 | F57: 4 | G57: =F57*E57 -> 2000
C58: 26 | D58: M. Obra Autosoportado 2100x800x800mm (Mecanica, Soldadura, Pintura, Armado) | E58: 600 | F58: 0 | G58: =F58*E58 -> 0
C59: 26 | D59: M. Obra Autosoportado 2100x900x800mm (Mecanica, Soldadura, Pintura, Armado) | E59: 700 | F59: 0 | G59: =F59*E59 -> 0
C60: 26 | D60: M. Obra Autosoportado 2100x(2)800x800mm (Mecanica, Soldadura, Pintura, Armado) | E60: 600 | F60: 0 | G60: =F60*E60 -> 0
C61: 26 | D61: M. Obra Autosoportado 2100x(3)800x800mm (Mecanica, Soldadura, Pintura, Armado) | E61: 600 | F61: 0 | G61: =F61*E61 -> 0
D62: M. Obra Autosoportado 2100x1000x700mm (Mecanica, Soldadura, Pintura, Armado) | E62: 1100 | F62: 0 | G62: =F62*E62 -> 0
G63: =SUM(G57:G57) -> 2000
C65: ITEM | D65: DISEÑO INGENIERIA | E65: PRECIO (S/) | F65: CANTIDAD | G65: SUB TOTAL
B66: DISEÑO INGENIERIA | C66: 27 | D66: Diseño Ingenieria Tableros Empotrados | E66: 10 | F66: 58 | G66: =F66*E66 -> 580
C67: 28 | D67: Diseño Ingenieria Tableros Adosados | E67: 10 | F67: 0 | G67: =F67*E67 -> 0
C68: 29 | D68: Diseño Ingenieria Tableros Autosoportados | E68: 100 | F68: 4 | G68: =F68*E68 -> 400
G69: =SUM(G66:G68) -> 980
D71: TOTAL MANO DE OBRA | G71: =G10+G19+G43+G63+G32+G69 -> #REF!
F73: T. Cambio | G73: 3.8
B75: COSTO DE MATERIALES
C77: ITEM | D77: DECRIPCION | E77: CANTIDAD | F77: UNIDAD | G77: PRECIO (S/)
B78: PLANCHA Y ACCESORIOS | C78: 30 | D78: Plancha LAF 1.5mm 1200x2400mm. | E78: 1 | F78: Und | G78: =30.2*G73 -> 114.76
C79: 31 | D79: Plancha LAF 2.0mm 1200x2400mm. | E79: 1 | F79: Und | G79: =40.24*G73 -> 152.912
C80: 32 | D80: Plancha LAF 2.5mm 1200x2400mm. | E80: 1 | F80: Und | G80: =53.5*G73 -> 203.3
D81: Plancha LAF 3mm 1200x2400mm. | E81: 1 | F81: Und | G81: =245/1.18 -> 207.62712
C82: 33 | D82: Plancha Galvanizada 1.5mm 1200x2400mm. | E82: 1 | F82: Und | G82: =34.31*G73 -> 130.378
C83: 34 | D83: Pintura polvo m2 | E83: 8 | F83: kg | G83: 19
C84: 35 | D84: Chapa Push boton | E84: 1 | F84: Und | G84: 6
C85: 36 | D85: Chapa Circular con llave metal MS705-1-1 TKL, ACSA | E85: 1 | F85: Pza | G85: 6.5 | H85: https://www.acsa.com.pe/tienda/tableros-y-gabinetes-metalicos/chapa-circular-c-llave-metal-ms705-1-1
C86: 37 | D86: Chapa para Autosoportado | E86: 1 | F86: Pza | G86: 88
C87: 38 | D87: Aislador 0.5/450 | E87: 1 | F87: Pza | G87: 1.86
C88: 39 | D88: Aislador 1/1000 | E88: 1 | F88: Pza | G88: 3.81
C89: 40 | D89: Prensa estopas PG 36 | E89: 1 | F89: Pza | G89: 7.5
B90: BARRAS DE COBRE | C90: 41 | D90: Barra de cobre de 5x40x1mt | E90: 1 | F90: m | G90: =500/6 -> 83.333333 | H90: 573
C91: 42 | D91: Barra de cobre de 5x30x1mt | E91: 1 | F91: m | G91: =338.625/6 -> 56.4375 | H91: 447
C92: 43 | D92: Barra de cobre de 5x20x1mt | E92: 1 | F92: m | G92: =246.98/6 -> 41.163333 | H92: 319
C93: 44 | D93: Barra de cobre de 3x25x1mt | E93: 1 | F93: m | G93: =191.43/6 -> 31.905 | H93: 287
C94: 45 | D94: Barra de cobre de 3x20x1mt | E94: 1 | F94: m | G94: =153.3375/6 -> 25.55625 | H94: 237
C95: 46 | D95: Barra de cobre de 3x15x1mt | E95: 1 | F95: m | G95: =114.86/6 -> 19.143333 | H95: 187
C96: 47 | D96: Panel de barras de cobre 06-08 polos, R, S, T, Princ. 3x20mm/Derivac. 2x10mm. | E96: 1 | F96: Jgo | G96: =110/1.18 -> 93.220339 | H96: 237A
C97: 48 | D97: Panel de barras de cobre 10-12 polos, R, S, T, Princ. 3x20mm/Derivac. 2x10mm. | E97: 1 | F97: Jgo | G97: =130/1.18 -> 110.16949
C98: 49 | D98: Panel de barras de cobre 14-16 polos, R, S, T, Princ. 3x20mm/Derivac. 2x10mm. | E98: 1 | F98: Jgo | G98: =150/1.18 -> 127.11864
C99: 50 | D99: Panel de barras de cobre 18-20 polos, R, S, T, Princ. 3x20mm/Derivac. 2x10mm. | E99: 1 | F99: Jgo | G99: =170/1.18 -> 144.0678
C100: 51 | D100: Panel de barras de cobre 22-24 polos, R, S, T, Princ. 3x20mm/Derivac. 2x10mm. | E100: 1 | F100: Jgo | G100: =190/1.18 -> 161.01695
C101: 52 | D101: Panel de barras de cobre 26-28 polos, R, S, T, Princ. 3x20mm/Derivac. 2x10mm. | E101: 1 | F101: Jgo | G101: =210/1.18 -> 177.9661
C102: 53 | D102: Panel de barras de cobre 30-32 polos, R, S, T, Princ. 3x20mm/Derivac. 2x10mm. | E102: 1 | F102: Jgo | G102: =230/1.18 -> 194.91525
C103: 54 | D103: Panel de barras de cobre 34-36 polos, R, S, T, Princ. 3x20mm/Derivac. 2x10mm. | E103: 1 | F103: Jgo | G103: =250/1.18 -> 211.86441
C104: 55 | D104: Panel de barras de cobre 38-40 polos, R, S, T, Princ. 3x20mm/Derivac. 2x10mm. | E104: 1 | F104: Jgo | G104: =270/1.18 -> 228.81356
C105: 56 | D105: Panel de barras de cobre 42-44 polos, R, S, T, Princ. 3x20mm/Derivac. 2x10mm. | E105: 1 | F105: Jgo | G105: =290/1.18 -> 245.76271
C106: 57 | D106: Panel de barras de cobre 46-48 polos, R, S, T, Princ. 3x20mm/Derivac. 2x10mm. | E106: 1 | F106: Jgo | G106: =320/1.18 -> 271.18644
C107: 58 | D107: Panel de barras de cobre 50-52 polos, R, S, T, Princ. 3x20mm/Derivac. 2x10mm. | E107: 1 | F107: Jgo | G107: =350/1.18 -> 296.61017
C108: 59 | D108: Panel de barras de cobre 54-56 polos, R, S, T, Princ. 3x20mm/Derivac. 2x10mm. | E108: 1 | F108: Jgo | G108: =360/1.18 -> 305.08475
C109: 60 | D109: Panel de barras de cobre 58-60 polos, R, S, T, Princ. 3x20mm/Derivac. 2x10mm. | E109: 1 | F109: Jgo | G109: =380/1.18 -> 322.0339
B110: CABLES | C110: 61 | D110: Cable NH-80, 2.5mm2, INDECO | E110: 1 | F110: m | G110: =165/1.18/100 -> 1.3983051
C111: 62 | D111: Cable NH-80, 4mm2, 32A, INDECO | E111: 1 | F111: m | G111: =245/1.18/100 -> 2.0762712
C112: 63 | D112: Cable NH-80, 6mm2, 41A, INDECO | E112: 1 | F112: m | G112: =378.78/1.18/100 -> 3.21
C113: 64 | D113: Cable NH-80, 10mm2, 57A, INDECO | E113: 1 | F113: m | G113: 5.1
C114: 65 | D114: Cable NH-80, 16mm2, 76A, INDECO | E114: 1 | F114: m | G114: 8.5
...

Sheet Cobre por polos
B2: COSTO SISTEMA DE BARRAS POR NUMERO DE POLOS
B4: ITEM | C4: SISTEMA DE BARRAS 06-08 POLOS | D4: UNIDAD | E4: CANTIDAD | F4: PRECIO S/ | G4: SUB TOTAL S/
B5: 06-08 POLOS | C5: =Materiales!D96 -> Panel de barras de cobre 06-08 polos, R, S, T, Princ. 3x20mm/Derivac. 2x10mm. | D5: Jgo | E5: 1 | F5: =Materiales!G96 -> 93.220339 | G5: =E5*F5 -> 93.220339
C6: Suples 3x20mm | D6: m | E6: =0.2*3 -> 0.6 | F6: 25.55625 | G6: =E6*F6 -> 15.33375
C7: Barra de cobre de 3x20x1mt | D7: Tierra | E7: =0.2 -> 0.2 | F7: 25.55625 | G7: =E7*F7 -> 5.11125
C8: Kits de pernos en general 08-14 polos | D8: Jgo | E8: 1 | F8: 10 | G8: =E8*F8 -> 10
C9: SISTEMA DE BARRAS 08-10 POLOS | G9: =SUM(G5:G8) -> 123.66534
B11: ITEM | C11: SISTEMA DE BARRAS 10-12 POLOS | D11: UNIDAD | E11: CANTIDAD | F11: PRECIO S/ | G11: SUB TOTAL S/
B12: 10-12 POLOS | C12: Panel de barras de cobre 10-12 polos, R, S, T, Princ. 3x20mm/Derivac. 2x10mm. | D12: Jgo | E12: 1 | F12: 110.16949 | G12: =E12*F12 -> 110.16949
C13: Suples 3x20mm | D13: m | E13: =0.2*3 -> 0.6 | F13: 25.55625 | G13: =E13*F13 -> 15.33375
C14: Barra de cobre de 3x20x1mt | D14: Tierra | E14: =0.2 -> 0.2 | F14: 25.55625 | G14: =E14*F14 -> 5.11125
C15: Kits de pernos en general 08-14 polos | D15: Jgo | E15: 1 | F15: 10 | G15: =E15*F15 -> 10
C16: =C11 -> SISTEMA DE BARRAS 10-12 POLOS | G16: =SUM(G12:G15) -> 140.61449
B18: ITEM | C18: SISTEMA DE BARRAS 14-16 POLOS | D18: UNIDAD | E18: CANTIDAD | F18: PRECIO S/ | G18: SUB TOTAL S/
B19: 14-16 POLOS | C19: Panel de barras de cobre 14-16 polos, R, S, T, Princ. 3x20mm/Derivac. 2x10mm. | D19: Jgo | E19: 1 | F19: 127.11864 | G19: =E19*F19 -> 127.11864
C20: Suples 3x20mm | D20: m | E20: =0.2*3 -> 0.6 | F20: 25.55625 | G20: =E20*F20 -> 15.33375
C21: Barra de cobre de 3x20x1mt | D21: Tierra | E21: =0.2 -> 0.2 | F21: 25.55625 | G21: =E21*F21 -> 5.11125
C22: Kits de pernos en general 08-14 polos | D22: Jgo | E22: 1 | F22: 10 | G22: =E22*F22 -> 10
C23: SISTEMA DE BARRAS 14-16 POLOS | G23: =SUM(G19:G22) -> 157.56364
B25: ITEM | C25: SISTEMA DE BARRAS 18-20 POLOS | D25: UNIDAD | E25: CANTIDAD | F25: PRECIO S/ | G25: SUB TOTAL S/
B26: 18-20 POLOS | C26: Panel de barras de cobre 18-20 polos, R, S, T, Princ. 3x20mm/Derivac. 2x10mm. | D26: Jgo | E26: 1 | F26: 144.0678 | G26: =E26*F26 -> 144.0678
C27: Suples 3x20mm | D27: m | E27: =0.2*3 -> 0.6 | F27: 25.55625 | G27: =E27*F27 -> 15.33375
C28: Barra de cobre de 3x20x1mt | D28: Tierra | E28: =0.2 -> 0.2 | F28: 25.55625 | G28: =E28*F28 -> 5.11125
C29: Kits de pernos en general 16-22 polos | D29: Jgo | E29: 1 | F29: 15 | G29: =E29*F29 -> 15
C30: SISTEMA DE BARRAS 18-20 POLOS | G30: =SUM(G26:G29) -> 179.5128
B32: ITEM | C32: SISTEMA DE BARRAS 22-24 POLOS | D32: UNIDAD | E32: CANTIDAD | F32: PRECIO S/ | G32: SUB TOTAL S/
B33: 22-24 POLOS | C33: Panel de barras de cobre 22-24 polos, R, S, T, Princ. 3x20mm/Derivac. 2x10mm. | D33: Jgo | E33: 1 | F33: 161.01695 | G33: =E33*F33 -> 161.01695
C34: Suples 3x20mm | D34: m | E34: =0.2*3 -> 0.6 | F34: 25.55625 | G34: =E34*F34 -> 15.33375
C35: Barra de cobre de 3x20x1mt | D35: Tierra | E35: =0.2 -> 0.2 | F35: 25.55625 | G35: =E35*F35 -> 5.11125
C36: Kits de pernos en general 16-22 polos | D36: Jgo | E36: 1 | F36: 15 | G36: =E36*F36 -> 15
C37: SISTEMA DE BARRAS 22-24 POLOS | G37: =SUM(G33:G36) -> 196.46195
B39: ITEM | C39: SISTEMA DE BARRAS 26-28 POLOS | D39: UNIDAD | E39: CANTIDAD | F39: PRECIO S/ | G39: SUB TOTAL S/
B40: 26-28 POLOS | C40: Panel de barras de cobre 26-28 polos, R, S, T, Princ. 3x20mm/Derivac. 2x10mm. | D40: Jgo | E40: 1 | F40: 177.9661 | G40: =E40*F40 -> 177.9661
C41: Suples 3x20mm | D41: m | E41: =0.2*3 -> 0.6 | F41: 25.55625 | G41: =E41*F41 -> 15.33375
C42: Barra de cobre de 3x20x1mt | D42: Tierra | E42: =0.2 -> 0.2 | F42: 25.55625 | G42: =E42*F42 -> 5.11125
C43: Kits de pernos en general 24-30 polos | D43: Jgo | E43: 1 | F43: 20 | G43: =E43*F43 -> 20
C44: SISTEMA DE BARRAS 26-28 POLOS | G44: =SUM(G40:G43) -> 218.4111
B46: ITEM | C46: SISTEMA DE BARRAS 30-32 POLOS | D46: UNIDAD | E46: CANTIDAD | F46: PRECIO S/ | G46: SUB TOTAL S/
B47: 30-32 POLOS | C47: Panel de barras de cobre 30-32 polos, R, S, T, Princ. 3x20mm/Derivac. 2x10mm. | D47: Jgo | E47: 1 | F47: 194.91525 | G47: =E47*F47 -> 194.91525
C48: Suples 3x20mm | D48: m | E48: =0.2*3 -> 0.6 | F48: 25.55625 | G48: =E48*F48 -> 15.33375
C49: Barra de cobre de 3x20x1mt | D49: Tierra | E49: =0.2 -> 0.2 | F49: 25.55625 | G49: =E49*F49 -> 5.11125
C50: Kits de pernos en general 24-30 polos | D50: Jgo | E50: 1 | F50: 20 | G50: =E50*F50 -> 20
C51: SISTEMA DE BARRAS 30-32 POLOS | G51: =SUM(G47:G50) -> 235.36025
B53: ITEM | C53: SISTEMA DE BARRAS 34-36 POLOS | D53: UNIDAD | E53: CANTIDAD | F53: PRECIO S/ | G53: SUB TOTAL S/
B54: 34-36 POLOS | C54: Panel de barras de cobre 34-36 polos, R, S, T, Princ. 3x20mm/Derivac. 2x10mm. | D54: Jgo | E54: 1 | F54: 211.86441 | G54: =E54*F54 -> 211.86441
C55: Suples 3x20mm | D55: m | E55: =0.2*3 -> 0.6 | F55: 25.55625 | G55: =E55*F55 -> 15.33375
C56: Barra de cobre de 3x20x1mt | D56: Tierra | E56: =0.2 -> 0.2 | F56: 25.55625 | G56: =E56*F56 -> 5.11125
C57: Kits de pernos en general 32-38 polos | D57: Jgo | E57: 1 | F57: 25 | G57: =E57*F57 -> 25
C58: SISTEMA DE BARRAS 34-36 POLOS | G58: =SUM(G54:G57) -> 257.30941
B60: ITEM | C60: SISTEMA DE BARRAS 38-40 POLOS | D60: UNIDAD | E60: CANTIDAD | F60: PRECIO S/ | G60: SUB TOTAL S/
B61: 38-40 POLOS | C61: Panel de barras de cobre 38-40 polos, R, S, T, Princ. 3x20mm/Derivac. 2x10mm. | D61: Jgo | E61: 1 | F61: 228.81356 | G61: =E61*F61 -> 228.81356
C62: Suples 3x20mm | D62: m | E62: =0.2*3 -> 0.6 | F62: 25.55625 | G62: =E62*F62 -> 15.33375
C63: Barra de cobre de 3x20x1mt | D63: Tierra | E63: =0.2 -> 0.2 | F63: 25.55625 | G63: =E63*F63 -> 5.11125
C64: Kits de pernos en general 32-38 polos | D64: Jgo | E64: 1 | F64: 25 | G64: =E64*F64 -> 25
C65: =C60 -> SISTEMA DE BARRAS 38-40 POLOS | G65: =SUM(G61:G64) -> 274.25856
B67: ITEM | C67: SISTEMA DE BARRAS 42-44 POLOS | D67: UNIDAD | E67: CANTIDAD | F67: PRECIO S/ | G67: SUB TOTAL S/
B68: 42-44 POLOS | C68: Panel de barras de cobre 42-44 polos, R, S, T, Princ. 3x20mm/Derivac. 2x10mm. | D68: Jgo | E68: 1 | F68: 245.76271 | G68: =E68*F68 -> 245.76271
C69: Suples 3x20mm | D69: m | E69: =0.2*3 -> 0.6 | F69: 25.55625 | G69: =E69*F69 -> 15.33375
C70: Barra de cobre de 3x20x1mt | D70: Tierra | E70: =0.2 -> 0.2 | F70: 25.55625 | G70: =E70*F70 -> 5.11125
C71: Kits de pernos en general 40-46 polos | D71: Jgo | E71: 1 | F71: 30 | G71: =E71*F71 -> 30
C72: =C67 -> SISTEMA DE BARRAS 42-44 POLOS | G72: =SUM(G68:G71) -> 296.20771
B74: ITEM | C74: SISTEMA DE BARRAS 46-48 POLOS | D74: UNIDAD | E74: CANTIDAD | F74: PRECIO S/ | G74: SUB TOTAL S/
B75: 46-48 POLOS | C75: Panel de barras de cobre 46-48 polos, R, S, T, Princ. 3x20mm/Derivac. 2x10mm. | D75: Jgo | E75: 1 | F75: 271.18644 | G75: =E75*F75 -> 271.18644
C76: Suples 3x20mm | D76: m | E76: =0.2*3 -> 0.6 | F76: 25.55625 | G76: =E76*F76 -> 15.33375
C77: Barra de cobre de 3x20x1mt | D77: Tierra | E77: =0.2 -> 0.2 | F77: 25.55625 | G77: =E77*F77 -> 5.11125
C78: Kits de pernos en general 40-46 polos | D78: Jgo | E78: 1 | F78: 30 | G78: =E78*F78 -> 30
C79: =C74 -> SISTEMA DE BARRAS 46-48 POLOS | G79: =SUM(G75:G78) -> 321.63144
B81: ITEM | C81: SISTEMA DE BARRAS 50-52 POLOS | D81: UNIDAD | E81: CANTIDAD | F81: PRECIO S/ | G81: SUB TOTAL S/
B82: 50-52 POLOS | C82: Panel de barras de cobre 50-52 polos, R, S, T, Princ. 3x20mm/Derivac. 2x10mm. | D82: Jgo | E82: 1 | F82: 296.61017 | G82: =E82*F82 -> 296.61017
C83: Suples 3x20mm | D83: m | E83: =0.2*3 -> 0.6 | F83: 25.55625 | G83: =E83*F83 -> 15.33375
C84: Barra de cobre de 3x20x1mt | D84: Tierra | E84: =0.2 -> 0.2 | F84: 25.55625 | G84: =E84*F84 -> 5.11125
C85: Kits de pernos en general 48-54 polos | D85: Jgo | E85: 1 | F85: 35 | G85: =E85*F85 -> 35
C86: =C81 -> SISTEMA DE BARRAS 50-52 POLOS | G86: =SUM(G82:G85) -> 352.05517
B88: ITEM | C88: SISTEMA DE BARRAS 54-56 POLOS | D88: UNIDAD | E88: CANTIDAD | F88: PRECIO S/ | G88: SUB TOTAL S/
B89: 54-56 POLOS | C89: Panel de barras de cobre 54-56 polos, R, S, T, Princ. 3x20mm/Derivac. 2x10mm. | D89: Jgo | E89: 1 | F89: 305.08475 | G89: =E89*F89 -> 305.08475
C90: Suples 3x20mm | D90: m | E90: =0.2*3 -> 0.6 | F90: 25.55625 | G90: =E90*F90 -> 15.33375
C91: Barra de cobre de 3x20x1mt | D91: Tierra | E91: =0.2 -> 0.2 | F91: 25.55625 | G91: =E91*F91 -> 5.11125
C92: Kits de pernos en general 48-54 polos | D92: Jgo | E92: 1 | F92: 35 | G92: =E92*F92 -> 35
C93: =C88 -> SISTEMA DE BARRAS 54-56 POLOS | G93: =SUM(G89:G92) -> 360.52975
B95: ITEM | C95: SISTEMA DE BARRAS 58-60 POLOS | D95: UNIDAD | E95: CANTIDAD | F95: PRECIO S/ | G95: SUB TOTAL S/
B96: 58-60 POLOS | C96: Panel de barras de cobre 58-60 polos, R, S, T, Princ. 3x20mm/Derivac. 2x10mm. | D96: Jgo | E96: 1 | F96: 322.0339 | G96: =E96*F96 -> 322.0339
C97: Suples 3x20mm | D97: m | E97: =0.2*3 -> 0.6 | F97: 25.55625 | G97: =E97*F97 -> 15.33375
C98: Barra de cobre de 3x20x1mt | D98: Tierra | E98: =0.2 -> 0.2 | F98: 25.55625 | G98: =E98*F98 -> 5.11125
C99: Kits de pernos en general 56-62 polos | D99: Jgo | E99: 1 | F99: 40 | G99: =E99*F99 -> 40
C100: =C95 -> SISTEMA DE BARRAS 58-60 POLOS | G100: =SUM(G96:G99) -> 382.4789

Sheet Cableado
B2: COSTO CABLEADO DE DIFERENCIALES
C4: INGRESAR CANTIDADES DE DIFERENCIALES
C5: Cantidad Diferenciales Bipolar 25A | D5: cant. | E5: 12
C6: Cantidad Diferenciales Bipolar 40A | D6: cant. | E6: 0
C7: Cantidad Diferenciales Tripolar + N 25A | D7: cant. | E7: 0
C8: Cantidad Diferenciales Tripolar + N 40A | D8: cant. | E8: 1
B10: N° POLOS | C10: CABLEADO 2 DIFERENCIALES | D10: UNIDAD | E10: CANTIDAD | F10: PRECIO S/ | G10: SUB TOTAL S/
B11: 2 | C11: =Materiales!D111 -> Cable NH-80, 4mm2, 32A, INDECO | D11: m | E11: =E5*2 -> 24 | F11: =Materiales!G111 -> 2.0762712 | G11: =E11*F11 -> 49.830508
B12: 2 | C12: =Materiales!D112 -> Cable NH-80, 6mm2, 41A, INDECO | D12: m | E12: =E6*2 -> 0 | F12: =Materiales!G112 -> 3.21 | G12: =E12*F12 -> 0
B13: 4 | C13: =Materiales!D111 -> Cable NH-80, 4mm2, 32A, INDECO | D13: m | E13: =E7*2 -> 0 | F13: =Materiales!G111 -> 2.0762712 | G13: =E13*F13 -> 0
B14: 4 | C14: =Materiales!D112 -> Cable NH-80, 6mm2, 41A, INDECO | D14: m | E14: =E8*2 -> 2 | F14: =Materiales!G112 -> 3.21 | G14: =E14*F14 -> 6.42
C15: =Materiales!D129 -> M. Menores (canaletas, terminales, marcadores, contillo, etc) 08-14 polos | D15: Jgo | E15: 1 | F15: =Materiales!G129 -> 15 | G15: =E15*F15 -> 15
C16: =C10 -> CABLEADO 2 DIFERENCIALES | G16: =SUM(G11:G15) -> 71.250508
C18: INGRESAR CANTIDADES DE DIFERENCIALES
C19: Cantidad Diferenciales Bipolar 25A | D19: cant. | E19: 1
C20: Cantidad Diferenciales Bipolar 40A | D20: cant. | E20: 0
C21: Cantidad Diferenciales Tripolar + N 25A | D21: cant. | E21: 0
C22: Cantidad Diferenciales Tripolar + N 40A | D22: cant. | E22: 0
B24: N° POLOS | C24: CABLEADO 3 DIFERENCIALES | D24: UNIDAD | E24: CANTIDAD | F24: PRECIO S/ | G24: SUB TOTAL S/
B25: 2 | C25: =Materiales!D111 -> Cable NH-80, 4mm2, 32A, INDECO | D25: m | E25: =E19*2 -> 2 | F25: =Materiales!G111 -> 2.0762712 | G25: =E25*F25 -> 4.1525424
B26: 2 | C26: =Materiales!D112 -> Cable NH-80, 6mm2, 41A, INDECO | D26: m | E26: =E20*2 -> 0 | F26: =Materiales!G112 -> 3.21 | G26: =E26*F26 -> 0
B27: 4 | C27: =Materiales!D111 -> Cable NH-80, 4mm2, 32A, INDECO | D27: m | E27: =E21*2 -> 0 | F27: =Materiales!G111 -> 2.0762712 | G27: =E27*F27 -> 0
B28: 4 | C28: =Materiales!D112 -> Cable NH-80, 6mm2, 41A, INDECO | D28: m | E28: =E22*2 -> 0 | F28: =Materiales!G112 -> 3.21 | G28: =E28*F28 -> 0
C29: =Materiales!D129 -> M. Menores (canaletas, terminales, marcadores, contillo, etc) 08-14 polos | D29: Jgo | E29: 1 | F29: =Materiales!G129 -> 15 | G29: =E29*F29 -> 15
C30: =C24 -> CABLEADO 3 DIFERENCIALES | G30: =SUM(G25:G29) -> 19.152542
C32: RESUMEN CABLEADO DIFERENCIALES 2 POLOS 25A
C33: DESCRIPCION | D33: AMPERAJE | E33: N° POLOS | F33: CANT. | G33: PRECIO (S/)
B34: 0 | C34: CABLEADO 0 DIFERENCIALES, 2P | D34: 25 | E34: 2 | F34: 0 | G34: 0
B35: 1 | C35: CABLEADO 1 DIFERENCIALES, 2P | D35: 25 | E35: 2 | F35: 1 | G35: 19.15
B36: 2 | C36: CABLEADO 2 DIFERENCIALES, 2P | D36: 25 | E36: 2 | F36: 2 | G36: 23.31
B37: 3 | C37: CABLEADO 3 DIFERENCIALES, 2P | D37: 25 | E37: 2 | F37: 3 | G37: 27.46
B38: 4 | C38: CABLEADO 4 DIFERENCIALES, 2P | D38: 25 | E38: 2 | F38: 4 | G38: 31.61
B39: 5 | C39: CABLEADO 5 DIFERENCIALES, 2P | D39: 25 | E39: 2 | F39: 5 | G39: 35.76
B40: 6 | C40: CABLEADO 6 DIFERENCIALES, 2P | D40: 25 | E40: 2 | F40: 6 | G40: 39.92
B41: 7 | C41: CABLEADO 7 DIFERENCIALES, 2P | D41: 25 | E41: 2 | F41: 7 | G41: 44.07
B42: 8 | C42: CABLEADO 8 DIFERENCIALES, 2P | D42: 25 | E42: 2 | F42: 8 | G42: 48.22
B43: 9 | C43: CABLEADO 9 DIFERENCIALES, 2P | D43: 25 | E43: 2 | F43: 9 | G43: 52.37
B44: 10 | C44: CABLEADO 10 DIFERENCIALES, 2P | D44: 25 | E44: 2 | F44: 10 | G44: 56.53
B45: 11 | C45: CABLEADO 11 DIFERENCIALES, 2P | D45: 25 | E45: 2 | F45: 11 | G45: 60.68
... B54: 20 | C54: CABLEADO 20 DIFERENCIALES, 2P | D54: 25 | E54: 2 | F54: 20 | G54: 98.05
C57: RESUMEN CABLEADO DIFERENCIALES 3P+N
C58: DESCRIPCION | D58: AMPERAJE | E58: N° POLOS | F58: CANT. | G58: PRECIO (S/)
C59: CABLEADO 1 DIFERENCIALES | D59: 25 | E59: 4 | F59: 1 | G59: 19.15
C60: CABLEADO 2 DIFERENCIALES | D60: 25 | E60: 4 | F60: 2 | G60: 23.31
C61: CABLEADO 3 DIFERENCIALES | D61: 25 | E61: 4 | F61: 3 | G61: 27.46
C62: CABLEADO 4 DIFERENCIALES | D62: 25 | E62: 4 | F62: 4 | G62: 31.61
C63: CABLEADO 5 DIFERENCIALES | D63: 25 | E63: 4 | F63: 5 | G63: 35.76
C64: CABLEADO 6 DIFERENCIALES | D64: 25 | E64: 4 | F64: 6 | G64: 39.92
C65: CABLEADO 7 DIFERENCIALES | D65: 25 | E65: 4 | F65: 7 | G65: 44.07
C66: CABLEADO 8 DIFERENCIALES | D66: 25 | E66: 4 | F66: 8 | G66: 48.22
C67: CABLEADO 9 DIFERENCIALES | D67: 25 | E67: 4 | F67: 9 | G67: 52.37
C70: MANO DE OBRA ELECTRICIDAD INTERRUPTORES | D70: PRECIO (S/) | I70: 3.8
C71: Mano de obra 6-10 polos (3-5 ITM) | D71: 70 | H71: =20 -> 20 | I71: =H71*I70 -> 76
C72: Mano de obra 12-16 polos (6-8 ITM) | D72: 100 | H72: 25 | I72: =H72*I70 -> 95
C73: Mano de obra 18-22 polos (9-11 ITM) | D73: 120 | H73: 30 | I73: =H73*I70 -> 114
C74: Mano de obra 24-28 polos (12-16 ITM) | D74: 140 | H74: 35 | I74: =H74*I70 -> 133
C75: Mano de obra 30-34 polos (18-22 ITM) | D75: 160 | H75: 40 | I75: =H75*I70 -> 152
C77: MANO DE OBRA ELECTRICIDAD DIFERENCIALES | D77: PRECIO (S/)
C78: Mano de obra 3-5 Diferenciales | D78: 40
C79: Mano de obra 6-8 Diferenciales | D79: 60
C80: Mano de obra 9-11 Diferenciales | D80: 80
C81: Mano de obra 12-16 Diferenciales | D81: 100
C82: Mano de obra 18-22 Diferenciales | D82: 120

Sheet Borneras
C2: COSTO CABLEADO A BORNERAS
C4: INGRESAR CANTIDADES DE BORNERAS
C5: =Materiales!D117 -> Bornera de 4mm2/10AWG, 32A, Riel Din, Tipo Tornillo, MRK-4, ONKA | D5: cant. | E5: 10
C6: =Materiales!D118 -> Bornera de 6mm2/8AWG, 41A, Riel Din, tipo Tornillo, MRK-6, ONKA | D6: cant. | E6: 5
C7: =Materiales!D119 -> Bornera de 10mm2/8AWG, 57A, Riel Din, tipo tornillo, MRK-10, ONKA | D7: cant. | E7: 0
C8: =Materiales!D120 -> Bornera de 16mm2/6AWG, 76A, Riel Din, tipo tornillo, MRK-16, ONKA | D8: cant. | E8: 0
C10: CABLEADO DE BORNERAS | D10: UNIDAD | E10: CANTIDAD | F10: PRECIO S/ | G10: SUB TOTAL S/
C11: =Materiales!D111 -> Cable NH-80, 4mm2, 32A, INDECO | D11: m | E11: =E5 -> 10 | F11: =Materiales!G111 -> 2.0762712 | G11: =E11*F11 -> 20.762712
C12: =Materiales!D112 -> Cable NH-80, 6mm2, 41A, INDECO | D12: m | E12: =E6 -> 5 | F12: =Materiales!G112 -> 3.21 | G12: =E12*F12 -> 16.05
C13: =Materiales!D113 -> Cable NH-80, 10mm2, 57A, INDECO | D13: m | E13: =E7 -> 0 | F13: =Materiales!G113 -> 5.1 | G13: =E13*F13 -> 0
C14: =Materiales!D114 -> Cable NH-80, 16mm2, 76A, INDECO | D14: m | E14: =E8 -> 0 | F14: =Materiales!G114 -> 8.5 | G14: =E14*F14 -> 0
C15: =C10 -> CABLEADO DE BORNERAS | G15: =SUM(G11:G14) -> 36.812712
C18: RESUMEN CABLEADO BORNERAS 4MM2
C19: DESCRIPCION | D19: CALIBRE | E19: AMPERAJE | F19: CANT. | G19: PRECIO (S/)
C20: CABLEADO 2 BORNERAS | D20: 4mm2 | E20: 32 | F20: 2 | G20: 4.15
C21: CABLEADO 3 BORNERAS | D21: 4mm2 | E21: 32 | F21: 3 | G21: 6.23
C22: CABLEADO 4 BORNERAS | D22: 4mm2 | E22: 32 | F22: 4 | G22: 8.31
C23: CABLEADO 5 BORNERAS | D23: 4mm2 | E23: 32 | F23: 5 | G23: 10.38
C24: CABLEADO 6 BORNERAS | D24: 4mm2 | E24: 32 | F24: 6 | G24: 12.46
C25: CABLEADO 7 BORNERAS | D25: 4mm2 | E25: 32 | F25: 7 | G25: 14.53
C26: CABLEADO 8 BORNERAS | D26: 4mm2 | E26: 32 | F26: 8 | G26: 16.61
C27: CABLEADO 9 BORNERAS | D27: 4mm2 | E27: 32 | F27: 9 | G27: 18.69
C28: CABLEADO 10 BORNERAS | D28: 4mm2 | E28: 32 | F28: 10 | G28: 20.76
C29: CABLEADO 11 BORNERAS | D29: 4mm2 | E29: 32 | F29: 11 | G29: 22.84
C30: CABLEADO 12 BORNERAS | D30: 4mm2 | E30: 32 | F30: 12 | G30: 24.92
C31: CABLEADO 13 BORNERAS | D31: 4mm2 | E31: 32 | F31: 13 | G31: 26.99
... C38: CABLEADO 20 BORNERAS | D38: 4mm2 | E38: 32 | F38: 20 | G38: 41.53

Sheet Empotrado 
B2: COSTO GABINETE EMPOTRADO
C4: Descripcion | E4: Precio (S/) | G4: Tipo de Cambio | H4: =Materiales!G73 -> 3.8
C5: =Materiales!D82 -> Plancha Galvanizada 1.5mm 1200x2400mm. | E5: =Materiales!G82 -> 130.378
C6: =Materiales!D78 -> Plancha LAF 1.5mm 1200x2400mm. | E6: =Materiales!G78 -> 114.76
C8: Dimensiones plancha | E8: 1200x2400mm.
C9: Area de plancha Plancha | E9: =1.2*2.4 -> 2.88
C11: Dimensiones del Gabinete (mm.)
C12: Alto | D12: 1400
C13: Ancho | D13: 600
C14: Profundidad | D14: 150
C16: Costo Material para Gabinete Empotrado | E16: =C5 -> Plancha Galvanizada 1.5mm 1200x2400mm. | T16: 30 dias
C17: Descripcion | E17: Unidad | F17: Cantidad
C18: Caja (laterales) | E18: m2 | F18: =+(D12)/1000*(D13-3+(D14-3)*2+10+10)/1000 -> 1.2754 | T18: 8 horas diarias
C19: Base y Techo | E19: m2 | F19: =+((D13-3-3+15+15)/1000*(D14-5+12+15)/1000)*2 -> 0.214656 | S19: H-H(Operario) | T19: =+W19/30/7 -> 9.5238095 | V19: Sueldo Operario | W19: 2000
E20: Total (m2) | F20: =SUM(F18:F19) -> 1.490056 | S20: H-H(Ayudante) | T20: =+W20/30/7 -> 7.6190476 | V20: Sueldo Ayudante | W20: 1600
E21: Cantidad Plancha | F21: =+F20/E9 -> 0.51738056
E22: Costo | F22: =+F21*E5 -> 67.455042
E23: Merma 30% | F23: =F22*0.3 -> 20.236513
E24: Costo + merma | F24: =F22+F23 -> 87.691555
C26: Costo Material para Gabinete Empotrado | E26: =C6 -> Plancha LAF 1.5mm 1200x2400mm.
C27: Descripcion | E27: Unidad | F27: Cantidad
C28: Tapapuerta | E28: m2 | F28: =+(D12+60)/1000*(D13+60)/1000 -> 0.9636
C29: Mandil | E29: m2 | F29: =+(D12-70+15+15)/1000*(D13-70+15+15)/1000 -> 0.7616
C30: Placa Base | E30: m2 | F30: =+(D12-70+15+15)/1000*(D13-70+15+15)/1000 -> 0.7616
C31: Borde superior e inferior | E31: m2 | F31: =+(D13-82)/1000*(151)/1000*2 -> 0.156436
C32: Borde Lateral | E32: m2 | F32: =+(D12+24)/1000*(132)/1000*2 -> 0.375936
E33: Total (m2) | F33: =SUM(F28:F32) -> 3.019172
E34: Cantidad Plancha | F34: =+F33/E9 -> 1.0483236
E35: Costo | F35: =+F34*E6 -> 120.30562
E36: Merma 30% | F36: =F35*0.3 -> 36.091685
E37: Costo + merma | F37: =F35+F36 -> 156.3973
C39: PINTADO, INSUMOS Y ACCESORIOS - GABINETE EMPOTRADO
C40: Descripción | D40: Cant. | E40: Und. | F40: P.U (S/) | G40: P.T (S/)
C41: =Materiales!D83 -> Pintura polvo m2 | D41: =(+F33)*2/5 -> 1.2076688 | E41: Kg | F41: =Materiales!G83 -> 19 | G41: =+F41*D41 -> 22.945707
C42: =Materiales!D142 -> Bisagra Piano para empotrado | D42: =D12/1000 -> 1.4 | E42: m | F42: =Materiales!G142 -> 20 | G42: =+F42*D42 -> 28
C43: =Materiales!D84 -> Chapa Push boton | D43: 4 | E43: Und | F43: =Materiales!G84 -> 6 | G43: =+F43*D43 -> 24
C44: =Materiales!D139 -> Pernos Gabinete empotrado | D44: 1 | E44: Glb. | F44: =Materiales!G139 -> 20 | G44: =+F44*D44 -> 20
C45: =Materiales!D138 -> Lijas y trapo industrial | D45: 1 | E45: Und | F45: =Materiales!G138 -> 2.5 | G45: =+F45*D45 -> 2.5
C46: =Materiales!D145 -> Portaplanos empotrado | D46: 1 | E46: Und | F46: =Materiales!G145 -> 10 | G46: =F46*D46 -> 10
C47: =Materiales!D149 -> Rotulo Logo peligro pintado | D47: 1 | E47: Glb. | F47: =Materiales!G149 -> 10 | G47: =+F47*D47 -> 10
C48: =Materiales!D150 -> Rotulo placa Nombre de tablero | D48: 1 | E48: Und | F48: =Materiales!G150 -> 5.5 | G48: =F48*D48 -> 5.5
C49: =Materiales!D151 -> Rotulo placa circuitos derivados | D49: 12 | E49: Und | F49: =Materiales!G151 -> 1.5 | G49: =F49*D49 -> 18
C50: =Materiales!D152 -> Embalaje Empotrado | D50: 1 | E50: Glb. | F50: =Materiales!G152 -> 10 | G50: =F50*D50 -> 10
C51: =Materiales!D155 -> Dossier, hojas, micas impresiones (Adosado-Empotrado) | D51: 1 | E51: Glb. | F51: =Materiales!G155 -> 10 | G51: =F51*D51 -> 10
C52: =Materiales!D157 -> Desgaste de Maquinarias Adosado y empotrado | D52: 1 | E52: Glb. | F52: =Materiales!G157 -> 50 | G52: =+F52*D52 -> 50
F53: Sub Total | G53: =SUM(G41:G52) -> 210.94571
F55: Costo Material | G55: =+G53+F37+F24 -> 455.03456
C57: PRECIOS EMPOTRADOS
C58: Dimensiones ( mm) | E58: Precio (S/) | F58: Costo Material | G58: M. Obra
C59: Gabinete Empotrado 1400x600x150mm. | E59: =F59+G59 -> 830.03 | F59: 455.03 | G59: =+Materiales!E42 -> 375
C60: Gabinete Empotrado 1200x600x150mm. | E60: =F60+G60 -> 716.03 | F60: 416.03 | G60: =Materiales!E41 -> 300
C61: Gabinete Empotrado 1000x600x150mm. | E61: =F61+G61 -> 602.02 | F61: 377.02 | G61: =Materiales!E39 -> 225 | J61: 407
C62: Gabinete Empotrado 800x450x150mm. | E62: =F62+G62 -> 454.02 | F62: 304.02 | G62: =Materiales!E37 -> 150 | J62: 315
C63: Gabinete Empotrado 900x450x150mm. | E63: =+F63+G63 -> 507.47 | F63: 319.97 | G63: =+Materiales!E38 -> 187.5
C64: Gabinete Empotrado 700x450x150mm. | E64: =F64+G64 -> 408.07 | F64: 288.07 | G64: =Materiales!E36 -> 120 | J64: 239
B67: PRECIOS ADOSADOS IP66

Sheet Adosado
B2: COSTO GABINETE ADOSADO
C4: Descripcion | E4: Precio (S/) | G4: Tipo de cambio | H4: =Materiales!G73 -> 3.8
C5: =+Materiales!D79 -> Plancha LAF 2.0mm 1200x2400mm. | E5: =+Materiales!G79 -> 152.912
C7: Dimensiones plancha | E7: 1200x2400mm.
C8: Area de plancha Plancha | E8: =1.2*2.4 -> 2.88
C10: Dimensiones del Gabinete (mm.)
C11: Alto | D11: 550
C12: Ancho | D12: 450
C13: Profundidad | D13: 150
C15: Costo Material para gabinete Adosado | E15: =C5 -> Plancha LAF 2.0mm 1200x2400mm.
C16: Descripcion | E16: Unidad | F16: Cantidad
C17: Caja | E17: m2 | F17: =+D11/1000*((D12-3)/1000+(D13-3)/1000*2+(30+12+8)/1000*2) -> 0.46255 | J17: MANO DE OBRA E INSUMOS - GABINETE ADOSADO
C18: Base | E18: m2 | F18: =+((D12-6+15+15)/1000*(D13-5+30+12+8+15)/1000) -> 0.09954 | J18: Descripción | K18: Cant. | L18: Unid. | M18: P.U (S/) | N18: P.T (S/)
C19: Techo | E19: m2 | F19: =+F18 -> 0.09954 | J19: Lijas | K19: 1 | L19: Unid. | M19: 1.2 | N19: =+M19*K19 -> 1.2
C20: Puerta | E20: m2 | F20: =+(D12-8+12+12)/1000*(D11-8+12+12)/1000 -> 0.263756 | J20: Trapos | K20: 2 | L20: Unid. | M20: 0.25 | N20: =+M20*K20 -> 0.5
C21: Placa Base | E21: m2 | F21: =+(D11-75+15+15)/1000*(D12-75+15+15)/1000 -> 0.204525 | J21: Pernos | K21: 1 | L21: Glb. | M21: 10 | N21: =+M21*K21 -> 10
C22: Mandil | E22: m2 | F22: =+F21 -> 0.204525 | J22: Logo Peligro | K22: 1 | L22: Glb. | M22: 10 | N22: =+M22*K22 -> 10
E23: Total (m2) | F23: =SUM(F17:F22) -> 1.334436 | J23: M.O. Mecanica | K23: 1 | L23: Glb. | M23: =(S12+S13)*2 -> 0 | N23: =+M23*K23 -> 0 | O23: =SUM(N23:N26) -> 0
E24: Cantidad Plancha | F24: =+(F23/E8) -> 0.46334583 | J24: M.O. Soldadura | K24: 1 | L24: Glb. | M24: =(S12+S13)*2.5 -> 0 | N24: =+M24*K24 -> 0
E25: Costo | F25: =+F24*E5 -> 70.851138 | J25: M.O. Pintura | K25: 1 | L25: Glb. | M25: =(S12+S13)*2.5 -> 0 | N25: =+M25*K25 -> 0
E26: Merma 30% | F26: =F25*0.3 -> 21.255341 | J26: M.O. Armado | K26: 1 | L26: Glb. | M26: =(S12+S13)*3 -> 0 | N26: =+M26*K26 -> 0
E27: Costo + merma | F27: =F25+F26 -> 92.106479 | J27: Bisagra | K27: 4 | L27: Unid. | M27: 5 | N27: =+M27*K27 -> 20
J28: Frisa | L28: m | M28: 3 | N28: =+M28*D37 -> 6
J29: Chapa | K29: 4 | L29: Unid. | M29: 8 | N29: =+M29*K29 -> 32
J30: Pintura | K30: =+F23/5*2 -> 0.5337744 | L30: Kg | M30: 18.5 | N30: =+M30*K30 -> 9.8748264
C31: PINTADO, INSUMOS Y ACCESORIOS - GABINETE EMPOTRADO | J31: Portaplanos | K31: 1 | L31: Glb. | M31: 10 | N31: =M31*K31 -> 10
C32: Descripción | D32: Cant. | E32: Und. | F32: P.U (S/) | G32: P.T (S/) | J32: Embalado | K32: 1 | L32: Glb. | M32: 10 | N32: =M32*K32 -> 10
C33: =Materiales!D83 -> Pintura polvo m2 | D33: =(+F23)*2/5 -> 0.5337744 | E33: Kg | F33: =Materiales!G83 -> 19 | G33: =+F33*D33 -> 10.141714 | M33: Sub-Total | N33: =SUM(N19:N32) -> 109.57483
C34: =Materiales!D143 -> Bisagra de 3 puntos HL011-1, Adosados | D34: 2 | E34: Und. | F34: =Materiales!G143 -> 5 | G34: =+F34*D34 -> 10
C35: =Materiales!D85 -> Chapa Circular con llave metal MS705-1-1 TKL, ACSA | D35: 1 | E35: Und | F35: =Materiales!G85 -> 6.5 | G35: =+F35*D35 -> 6.5 | J35: Costo Total | K35: =+N33+F25+P17 -> 180.42596 | L35: Margen | M35: 0.3
C36: =Materiales!D140 -> Pernos Gabinete adosado | D36: 1 | E36: Glb. | F36: =Materiales!G140*0.4 -> 8 | G36: =+F36*D36 -> 8 | J36: Margen | K36: =+M35*K35 -> 54.127789
C37: =Materiales!D136 -> Frisa plana Adhesiva 1" X 5 MM | D37: =+D11/1000*2+D12/1000*2 -> 2 | E37: m | F37: =Materiales!G136 -> 2.12 | G37: =F37*D37 -> 4.24
C38: =Materiales!D138 -> Lijas y trapo industrial | D38: 1 | E38: Und | F38: =Materiales!G138 -> 2.5 | G38: =+F38*D38 -> 2.5 | J38: P.Venta | K38: =+K36+K35 -> 234.55375
C39: =Materiales!D146 -> Portaplanos adosado | D39: 1 | E39: Glb. | F39: =Materiales!G146*0.5 -> 5 | G39: =+F39*D39 -> 5
C40: =Materiales!D149 -> Rotulo Logo peligro pintado | D40: 1 | E40: Und | F40: =Materiales!G149*0.8 -> 8 | G40: =F40*D40 -> 8
C41: =Materiales!D150 -> Rotulo placa Nombre de tablero | D41: 1 | E41: Glb. | F41: =Materiales!G150 -> 5.5 | G41: =F41*D41 -> 5.5 | J41: 24
C42: =Materiales!D151 -> Rotulo placa circuitos derivados | D42: 12 | E42: Und | F42: =Materiales!G151 -> 1.5 | G42: =F42*D42 -> 18 | J42: 12
C43: =Materiales!D153 -> Embalaje Adosado | D43: 1 | E43: Und | F43: =Materiales!G153 -> 10 | G43: =F43*D43 -> 10
C44: =Materiales!D155 -> Dossier, hojas, micas impresiones (Adosado-Empotrado) | D44: 1 | E44: Glb. | F44: =Materiales!G155 -> 10 | G44: =F44*D44 -> 10
C45: =Materiales!D157 -> Desgaste de Maquinarias Adosado y empotrado | D45: 1 | E45: Glb. | F45: =Materiales!G157*0.3 -> 15 | G45: =+F45*D45 -> 15
F46: Sub Total | G46: =SUM(G33:G45) -> 112.88171
F48: Costo Material | G48: =+G46+F27 -> 204.98819
C50: PRECIOS ADOSADOS
C51: Dimensiones ( mm) | E51: Precio (S/) | F51: Costo Material | G51: M. Obra
C52: Gabinete Adosado 1400x600x150mm. | E52: =F52+G52 -> 804.62 | F52: 429.62 | G52: =+Materiales!E52 -> 375
C53: Gabinete Adosado 1200x600x150mm. | E53: =F53+G53 -> 711.49 | F53: 396.49 | G53: =Materiales!E51 -> 315
C54: Gabinete Adosado 1000x450x150mm. (alto x ancho x profundidad) dimensiones aproximadas | E54: =407+90 -> 497 | F54: 324 | G54: =+Materiales!E48 -> 225
C55: Gabinete Adosado 1100x800x300mm. (alto x ancho x profundidad) dimensiones aproximadas | E55: =630+190 -> 820 | F55: 363.36 | G55: =Materiales!E49 -> 240 | I55: 407
C56: Gabinete Adosado 900x800x300mm. (alto x ancho x profundidad) dimensiones aproximadas | E56: =564+180 -> 744 | F56: 363.36 | G56: =Materiales!E49 -> 240 | I56: 407
C57: Gabinete Adosado 850x800x300mm. (alto x ancho x profundidad) dimensiones aproximadas | E57: =564+165 -> 729 | F57: 363.36 | G57: =Materiales!E51 -> 315 | I57: 407
C58: Gabinete Adosado 800x800x300mm. (alto x ancho x profundidad) dimensiones aproximadas | E58: =564+150 -> 714 | F58: 363.36 | G58: =Materiales!E50 -> 277.5 | I58: 407
C59: Gabinete Adosado 800x450x150mm. (alto x ancho x profundidad) dimensiones aproximadas | E59: =315+70 -> 385 | F59: 298.01 | G59: =Materiales!E47 -> 150 | I59: 315
C60: Gabinete Adosado 700x450x150mm. (alto x ancho x profundidad) dimensiones aproximadas | E60: =239+80 -> 319 | F60: 285.01 | G60: =Materiales!E46 -> 120 | I60: 239
C61: Gabinete Adosado 700x500x200mm. (alto x ancho x profundidad) dimensiones aproximadas | E61: =SUM(F61:G61) -> 341.6 | F61: 251.6 | G61: 90 | I61: 239
C62: Gabinete Adosado 550x450x150mm. (alto x ancho x profundidad) dimensiones aproximadas | E62: =SUM(F62:G62) -> 294.99 | F62: 204.99 | G62: 90 | I62: 239
C63: Gabinete Metalico 400x500x250mm. (Alto x Ancho x Profundidad) | E63: =+F63+G63 -> 218.85 | F63: 158.85 | G63: 60 | I63: 239
C64: Gabinete Metalico 1000x700x300mm. (Alto x Ancho x Profundidad) | E64: 466.62 | F64: =258.45+143.64 -> 402.09 | G64: 95 | I64: 239
C65: Gabinete Adosado 900x700x200mm. (alto x ancho x profundidad) dimensiones aproximadas | E65: =+F65+G65 -> 447.34 | F65: 352.34 | G65: 95 | I65: 239
C67: Dimensiones ( mm) | E67: Precio O.C. Intelsac (S/) | F67: Precio Venta Costo (S/)
C68: 700x450x180 | E68: 455.51 | F68: 477.07
C69: 700x500x180 | E69: 488.27 | F69: 487.67
C70: 700x600x180 | E70: 509.84 | F70: 508.87
C71: 700x600x200 | E71: 555.67 | F71: 512.16
C72: 800x600x180 | E72: 558.06 | F72: 527.33
C73: 900x600x180 | E73: 590.51 | F73: 545.79
C74: 900x800x180 | E74: 656.44 | F74: 598.44
C75: 1000x800x180 | E75: 794.27 | F75: 622.02
C76: 1000x800x200 | E76: 839.87 | F76: 626.55
C77: 1000x800x300 | E77: 950.15 | F77: 649.21
C78: 1100x800x180 | E78: 930.35 | F78: 645.6
C79: 1100x800x200 | E79: 948.42 | F79: 650.38
... C85: 1400x800x200 | E85: 1201.94 | F85: 721.88

Sheet Autosoportado
B2: COSTO GABINETE AUTOSOPORTADO
C4: Descripcion | E4: Precio (S/) | G4: Tipo de Cambio | H4: 3.8 | M4: dimensiones plancha | O4: area plancha
C5: =+Materiales!$D$81 -> Plancha LAF 3mm 1200x2400mm. | E5: =+Materiales!$G$81 -> 207.62712
C6: =+Materiales!$D$81 -> Plancha LAF 3mm 1200x2400mm. | E6: =+Materiales!$G$81 -> 207.62712
C7: =+Materiales!$D$81 -> Plancha LAF 3mm 1200x2400mm. | E7: =+Materiales!$G$81 -> 207.62712
C9: Dimensiones plancha | E9: 1200x2400mm.
C10: Area de plancha Plancha | E10: =1.2*2.4 -> 2.88
C12: Dimensiones del Gabinete (mm.) | M12: 1200x2400x1450mm. | P12: mm.
C13: Alto | D13: 2000
C14: Ancho | D14: 800
C15: Profundidad | D15: 450
C17: Costo Material: Cuerpo, Techo y puerta | F17: =C6 -> Plancha LAF 3mm 1200x2400mm. | S17: 8 horas diarias
C18: Descripcion | E18: A1 | F18: A2 | G18: AT
C19: Techo | E19: =+(D14-4+(46+25+18)*2)/1000 -> 0.974 | F19: =+(D15-4+25+18+46+46+15+10)/1000 -> 0.606 | G19: =+F19*E19 -> 0.590244 | R19: Hora-Hombre(Operario) | S19: =+V19/30/8 -> 8.3333333 | U19: Sueldo | V19: 2000
C20: Puerta | E20: =+(D14-5-4+20+10+18)/1000*2 -> 1.678 | F20: =+(D13-100-5-4+20+20)/1000 -> 1.931 | G20: =+F20*E20 -> 3.240218 | R20: Hora-Hombre(Ayudante) | S20: =+V20/30/8 -> 6.6666667 | U20: Sueldo | V20: 1600
C21: Parante Posterior | E21: =+(D13-100+4)/1000 -> 1.904 | F21: =+(180)/1000 -> 0.18 | G21: =+F21*E21*2 -> 0.68544
C22: Parante Frontal | E22: =+(D13-100+4)/1000 -> 1.904 | F22: =+(162)/1000 -> 0.162 | G22: =+F22*E22*2 -> 0.616896
C23: Base Posterior | E23: =+(D14-4)/1000 -> 0.796 | F23: =+(119)/1000 -> 0.119 | G23: =+F23*E23 -> 0.094724
C24: Base Frontal | E24: =+(D14-4)/1000 -> 0.796 | F24: =+(137)/1000 -> 0.137 | G24: =+F24*E24 -> 0.109052
C25: Base Lateral | E25: =+(D15-4)/1000 -> 0.446 | F25: =+(137)/1000 -> 0.137 | G25: =+F25*E25*2 -> 0.122204
F26: Total (m2) | G26: =SUM(G19:G25) -> 5.458778
F27: Cantidad Plancha | G27: =G26/E10 -> 1.895409
F28: Costo | G28: =+G27*E6 -> 393.53832
F29: Merma 30% | G29: =G28*0.3 -> 118.06149
F30: Costo + merma | G30: =G28+G29 -> 511.59981
C32: Costo Material: Paneles posteriores y laterales | F32: =C5 -> Plancha LAF 3mm 1200x2400mm.
C33: Panel Posterior | E33: =+(D14-50-50-3-4+18+18)/1000 -> 0.729 | F33: =+(D13-100-50-50-3-4+18+18)/1000 -> 1.829 | G33: =+(D14-50-50-3-4+18+18)/1000*(D13-100-50-50-3-4+18+18)/1000 -> 1.333341
C34: Panel Lateral | E34: =+(D15-50-50-3-4+18+18)/1000 -> 0.379 | F34: =+(D13-100-50-50-3-4+18+18)/1000 -> 1.829 | G34: =+((D15-50-50-3-4+18+18)/1000*(D13-100-50-50-3-4+18+18)/1000)*2 -> 1.386382
F35: Total (m2) | G35: =SUM(G33:G34) -> 2.719723
F36: Cantidad Plancha | G36: =G35/E10 -> 0.94434826
F37: Costo | G37: =+G36*E6 -> 196.07231
F38: Merma 30% | G38: =G37*0.3 -> 58.821693
F39: Costo + merma | G39: =G37+G38 -> 254.894
C41: Costo Material: Zocalo | F41: =C7 -> Plancha LAF 3mm 1200x2400mm.
C42: Zócalo Frontal | G42: =+(D14-5)/1000*(212)/1000 -> 0.16854
C43: Zócalo posterior | G43: =+(D14-5)/1000*(212)/1000 -> 0.16854
C44: Zócalo lateral | G44: =+(D15-5)/1000*(212)/1000 -> 0.09434
F45: Total (m2) | G45: =SUM(G42:G44) -> 0.43142
F46: Cantidad Plancha | G46: =+G45/E10 -> 0.14979861
F47: Costo | G47: =+G46*E7 -> 31.102254
F48: Merma 30% | G48: =G47*0.3 -> 9.3306762
F49: Costo + merma | G49: =G47+G48 -> 40.43293
C51: Costo Material: Mandil y Soportes | F51: =C6 -> Plancha LAF 3mm 1200x2400mm.
C52: Mandil | E52: =+(D14-150+15+15-3)/1000 -> 0.677 | F52: =+(D13-200-4+15+15)/1000 -> 1.826 | G52: =+(D14-150+15+15-3)/1000*(D13-200-4+15+15)/1000 -> 1.236202
C53: Soportes | E53: =+(D14-150+15+15-3)/1000 -> 0.677 | F53: =+(D13-200-4+15+15)/1000 -> 1.826 | G53: =E53*F53 -> 1.236202
F54: Cantidad Plancha | G54: =SUM(G52:G53)/E10 -> 0.85847361
F55: Costo | G55: =+G54*E6 -> 178.2424
F56: Merma 30% | G56: =G55*0.3 -> 53.472721
F57: Costo + merma | G57: =G55+G56 -> 231.71512
C59: Costo Material: Tapa Inferior | F59: =C5 -> Plancha LAF 3mm 1200x2400mm.
C60: Tapa inferior | E60: =+(D14-50+15+15-3)/1000 -> 0.777 | F60: =+(D15-100-4+15+15)/1000 -> 0.376 | G60: =+(D14-50+15+15-3)/1000*(D15-100-4+15+15)/1000 -> 0.292152
F61: Cantidad Plancha | G61: =G60/E10 -> 0.10144167
F62: Costo | G62: =+G61*E5 -> 21.062041
F63: Merma 30% | G63: =G62*0.3 -> 6.3186123
F64: Costo + merma | G64: =G62+G63 -> 27.380653
E66: Total costo Planchas LAF | G66: =G30+G39+G49+G57+G64 -> 1066.0225 | I66: 567.93 | J66: =G66-I66 -> 498.09252
C68: PINTADO, INSUMOS Y ACCESORIOS - GABINETE AUTOSOPORTADO
C69: Descripción | D69: Cant. | E69: Und. | F69: P.U (S/) | G69: P.T (S/)
C70: =Materiales!D83 -> Pintura polvo m2 | D70: =(+G45+G35+G26+G52+G60)/4*2 -> 5.0691375 | E70: Kg | F70: =Materiales!G83 -> 19 | G70: =+F70*D70 -> 96.313613
C71: =Materiales!D144 -> Bisagra Autosoportados | D71: 4 | E71: Und. | F71: 25 | G71: =+F71*D71 -> 100
C72: =Materiales!D86 -> Chapa para Autosoportado | D72: 1 | E72: Und. | F72: =Materiales!G86 -> 88 | G72: =+F72*D72 -> 88
C73: =Materiales!D141 -> Pernos Gabinete autosoportado | D73: 1 | E73: Glb. | F73: =Materiales!G141 -> 40 | G73: =+F73*D73 -> 40
C74: =Materiales!D136 -> Frisa plana Adhesiva 1" X 5 MM | D74: =6*2 -> 12 | E74: m | F74: =Materiales!G136 -> 2.12 | G74: =+F74*D74 -> 25.44
C75: =Materiales!D138 -> Lijas y trapo industrial | D75: 3 | E75: Und. | F75: =Materiales!G138*2 -> 5 | G75: =+F75*D75 -> 15
C76: =Materiales!D149 -> Rotulo Logo peligro pintado | D76: 1 | E76: Glb. | F76: =Materiales!G149 -> 10 | G76: =+F76*D76 -> 10
C77: =Materiales!D147 -> Portaplanos Autosoportado | D77: 1 | E77: Glb. | F77: =Materiales!G147 -> 45 | G77: =F77*D77 -> 45 | K77: =104/1.18 -> 88.135593
C78: =Materiales!D150 -> Rotulo placa Nombre de tablero | D78: 1 | E78: Glb. | F78: =Materiales!G150 -> 5.5 | G78: =F78*D78 -> 5.5
C79: =Materiales!D151 -> Rotulo placa circuitos derivados | D79: 20 | E79: Und. | F79: =Materiales!G151 -> 1.5 | G79: =F79*D79 -> 30
C80: =Materiales!D154 -> Embalaje Autosoportado | D80: 1 | E80: Und. | F80: =Materiales!G154 -> 50 | G80: =D80*F80 -> 50
C81: =Materiales!D156 -> Dossier, hojas, micas impresiones (Autosoportado) | D81: 1 | E81: Glb. | F81: =Materiales!G156 -> 50 | G81: =F81*D81 -> 50
C82: =Materiales!D158 -> Desgaste de Maquinarias Autosoportado | D82: 1 | E82: Glb. | F82: =Materiales!G158 -> 100 | G82: =F82*D82 -> 100
C83: =Materiales!D148 -> Cancamos de izaje | D83: 4 | E83: Glb. | F83: =Materiales!G148 -> 25 | G83: =F83*D83 -> 100
F84: Sub Total | G84: =SUM(G70:G83) -> 755.25361
F86: Costo Material | G86: =G84+G66 -> 1821.2761
C89: PRECIOS AUTOSOPORTADOS
C90: Dimensiones ( mm) | E90: Precio (S/) | F90: Costo Material | G90: M. Obra | H90: Refuerzo en puerta para aire acondicionado
C91: 1 PUERTA
C92: Gabinete Autosoportado 1800x600x450mm. (Alto x ancho x profundidad) | E92: =+E93 -> 2575.73 | F92: 1715.15 | G92: =+G93 -> 860.58
C93: Gabinete Autosoportado 1800x800x450mm. (Alto x ancho x profundidad) | E93: =F93+G93 -> 2575.73 | F93: 1715.15 | G93: =+'M. Obra Autosoportado'!D90 -> 860.58
C94: Gabinete Autosoportado 2000x800x450mm. (Alto x ancho x profundidad) | E94: =+F94+G94 -> 2780.86 | F94: 1821.28 | G94: =+'M. Obra Autosoportado'!D91 -> 959.58
C95: Gabinete Autosoportado 2100x800x600mm. (Alto x ancho x profundidad) | E95: =F95+G95 -> 2979.42 | F95: 1968.71 | G95: =+'M. Obra Autosoportado'!D92 -> 1010.71
C96: 2 PUERTAS
C97: Gabinete Autosoportado 2100x1000(2 Puertas)x700mm. (Alto x ancho x profundidad) | E97: =(F97+G97)+H97 -> 3930.25 | F97: 2275.79 | G97: =+'M. Obra Autosoportado'!D93 -> 1359.46 | H97: 295
C98: Gabinete Autosoportado 2200x1000(2 Puertas)x700mm. (Alto x ancho x profundidad) | E98: =(F98+G98)+H98 -> 4003.61 | F98: 2344.15 | G98: =+'M. Obra Autosoportado'!D93 -> 1359.46 | H98: 300
C99: Gabinete Autosoportado 2200x1200(2 Puertas)x700mm. (Alto x ancho x profundidad) | E99: =(F99+G99)+H99 -> 4475.92 | F99: 2598.46 | G99: =+'M. Obra Autosoportado'!D94 -> 1557.46 | H99: 320
C100: Gabinete Autosoportado 2400x1200(2 Puertas)x700mm. (Alto x ancho x profundidad) | E100: =(F100+G100)+H100 -> 4242.1383 | F100: 2755.43 | G100: =+'M. Obra Autosoportado'!D95 -> 1136.7083 | H100: 350

Sheet M. Obra Autosoportado
B2: COSTO DE MANO DE OBRA PLANTA, ADMINISTRATIVOS Y SERVICIOS
I4: Dias de trabajo | J4: 30
I5: Horas de trabajo | J5: 8
B7: MANO DE OBRA GABINETE AUTOSOPORTADO
E9: Con beneficios | H9: POR 1 TABLERO AUTOSOPORTADO | P9: POR 10 TABLEROS | S9: POR 50 TABLEROS | V9: POR 100 TABLEROS
B10: MANO DE OBRA PLANTA | D10: Sueldos (S/) | E10: 1.35 | F10: COSTO POR DIA | G10: COSTO POR HORA | H10: Tiempo trabajo (Hora) | I10: Dias de trabajo | J10: Costo trabajo (S/) | P10: Dias de trabajo | Q10: Tiempo trabajo (Hora) | R10: Costo trabajo (S/) | S10: Dias de trabajo | T10: Tiempo trabajo (Hora) | U10: Costo trabajo (S/) | V10: Dias de trabajo | W10: Tiempo trabajo (Hora) | X10: Costo trabajo (S/)
B11: Mecanica | C11: Operario | D11: 2400 | E11: =+D11*E10 -> 3240 | F11: =+E11/J4 -> 108 | G11: =+F11/J5 -> 13.5 | I11: 1 | J11: =+I11*F11 -> 108 | P11: - | Q11: 3 | R11: =+Q11*G11 -> 40.5 | S11: 1.5 | T11: - | U11: =+S11*F11 -> 162 | V11: 2.5 | W11: - | X11: =+V11*F11 -> 270
C12: Ayudante | D12: 2000 | E12: =+D12*E10 -> 2700 | F12: =+E12/J4 -> 90 | G12: =+F12/J5 -> 11.25 | I12: 1 | J12: =+I12*F12 -> 90 | P12: - | Q12: 3 | R12: =+Q12*G12 -> 33.75 | S12: 1.5 | T12: - | U12: =+S12*F12 -> 135 | V12: 2.5 | W12: - | X12: =+V12*F12 -> 225
B13: Soldadura | C13: Operario | D13: 2400 | E13: =+D13*E10 -> 3240 | F13: =+E13/J4 -> 108 | G13: =+F13/J5 -> 13.5 | I13: 1 | J13: =+I13*F13 -> 108 | P13: - | Q13: 5 | R13: =+Q13*G13 -> 67.5 | S13: 1 | T13: - | U13: =+S13*F13 -> 108 | V13: 2.5 | W13: - | X13: =+V13*F13 -> 270
C14: Ayudante | D14: 2000 | E14: =+D14*E10 -> 2700 | F14: =+E14/J4 -> 90 | G14: =+F14/J5 -> 11.25 | I14: 1 | J14: =+I14*F14 -> 90 | P14: - | Q14: 5 | R14: =+Q14*G14 -> 56.25 | S14: 1 | T14: - | U14: =+S14*F14 -> 90 | V14: 2.5 | W14: - | X14: =+V14*F14 -> 225
B15: Pintura | C15: operario | D15: 2400 | E15: =+D15*E10 -> 3240 | F15: =+E15/J4 -> 108 | G15: =+F15/J5 -> 13.5 | I15: 1 | J15: =+I15*F15 -> 108 | P15: 0.5 | Q15: - | R15: =+P15*F15 -> 54 | S15: 1.5 | T15: - | U15: =+S15*F15 -> 162 | V15: 3 | W15: - | X15: =+V15*F15 -> 324
C16: Ayudante | D16: 2000 | E16: =+D16*E10 -> 2700 | F16: =+E16/J4 -> 90 | G16: =+F16/J5 -> 11.25 | I16: 1 | J16: =+I16*F16 -> 90 | P16: 0.5 | Q16: - | R16: =+P16*F16 -> 45 | S16: 1.5 | T16: - | U16: =+S16*F16 -> 135 | V16: 3 | W16: - | X16: =+V16*F16 -> 270
B17: Barras | C17: operario | D17: 2400 | E17: =+D17*E10 -> 3240 | F17: =+E17/J4 -> 108 | G17: =+F17/J5 -> 13.5 | H17: - | J17: =+I17*F17 -> 0 | P17: - | Q17: 6 | R17: =+Q17*G17 -> 81 | S17: 1.5 | T17: - | U17: =+S17*F17 -> 162 | V17: 3 | W17: - | X17: =+V17*F17 -> 324
C18: Ayudante | D18: 2000 | E18: =+D18*E10 -> 2700 | F18: =+E18/J4 -> 90 | G18: =+F18/J5 -> 11.25 | H18: - | J18: =+I18*F18 -> 0 | P18: - | Q18: 6 | R18: =+Q18*G18 -> 67.5 | S18: 1.5 | T18: - | U18: =+S18*F18 -> 135 | V18: 3 | W18: - | X18: =+V18*F18 -> 270
B19: Ensamble | C19: Operario | D19: 2400 | E19: =+D19*E10 -> 3240 | F19: =+E19/J4 -> 108 | G19: =+F19/J5 -> 13.5 | H19: - | I19: 1 | J19: =+I19*F19 -> 108 | P19: 1 | Q19: - | R19: =+P19*F19 -> 108 | S19: 2.5 | T19: - | U19: =+S19*F19 -> 270 | V19: 4 | W19: - | X19: =+V19*F19 -> 432
C20: Ayudante | D20: 2000 | E20: =+D20*E10 -> 2700 | F20: =+E20/J4 -> 90 | G20: =+F20/J5 -> 11.25 | H20: - | I20: 1 | J20: =+I20*F20 -> 90 | P20: 1 | Q20: - | R20: =+P20*F20 -> 90 | S20: 2.5 | T20: - | U20: =+S20*F20 -> 225 | V20: 4 | W20: - | X20: =+V20*F20 -> 360
B21: Embalaje | C21: Operario | D21: 2400 | E21: =+D21*E10 -> 3240 | F21: =+E21/J4 -> 108 | G21: =+F21/J5 -> 13.5 | H21: 1 | J21: =+H21*G21 -> 13.5 | P21: - | Q21: 2 | R21: =+Q21*G21 -> 27 | S21: - | T21: 5 | U21: =+T21*G21 -> 67.5 | V21: 1.5 | W21: - | X21: =+V21*F21 -> 162
C22: Ayudante | D22: 2000 | E22: =+D22*E10 -> 2700 | F22: =+E22/J4 -> 90 | G22: =+F22/J5 -> 11.25 | H22: 1 | J22: =+H22*G22 -> 11.25 | P22: - | Q22: 2 | R22: =+Q22*G22 -> 22.5 | S22: - | T22: 5 | U22: =+T22*G22 -> 56.25 | V22: 1.5 | W22: - | X22: =+V22*F22 -> 135
B23: Almacen | C23: Operario | D23: 2400 | E23: =+D23*E10 -> 3240 | F23: =+E23/J4 -> 108 | G23: =+F23/J5 -> 13.5 | H23: 1 | J23: =+H23*G23 -> 13.5 | P23: 1 | Q23: - | R23: =+P23*F23 -> 108 | S23: 1 | T23: - | U23: =+S23*F23 -> 108 | V23: 1 | W23: - | X23: =+V23*F23 -> 108
C24: Ayudante | D24: 2000 | E24: =+D24*E10 -> 2700 | F24: =+E24/J4 -> 90 | G24: =+F24/J5 -> 11.25 | H24: 1 | J24: =+H24*G24 -> 11.25 | P24: 1 | Q24: - | R24: =+P24*F24 -> 90 | S24: 1 | T24: - | U24: =+S24*F24 -> 90 | V24: 1 | W24: - | X24: =+V24*F24 -> 90
J25: =SUM(J11:J24) -> 841.5
E28: Con beneficios | H28: POR 1 TABLERO AUTOSOPORTADO
B29: MANO DE OBRA PLANTA | D29: Sueldos (S/) | E29: 1.35 | F29: COSTO POR DIA | G29: COSTO POR HORA | H29: Tiempo trabajo (Hora) | I29: Dias de trabajo | J29: Costo trabajo (S/)
B30: Electricidad | C30: Operario | D30: 2400 | E30: =+D30*E10 -> 3240 | F30: =+E30/J4 -> 108 | G30: =+F30/J5 -> 13.5 | H30: - | I30: 3 | J30: =+I30*F30 -> 324
C31: Ayudante 1 | D31: 2000 | E31: =+D31*E10 -> 2700 | F31: =+E31/J4 -> 90 | G31: =+F31/J5 -> 11.25 | H31: - | I31: 3 | J31: =+I31*F31 -> 270
C32: Ayudante 2 | D32: 1600 | E32: =+D32*E10 -> 2160 | F32: =+E32/J4 -> 72 | G32: =+F32/J5 -> 9 | H32: - | I32: 3 | J32: =+I32*F32 -> 216
J33: =+SUM(J30:J32) -> 810
E36: Con beneficios | H36: POR 1 TABLERO AUTOSOPORTADO
B37: M. DE OBRA (TIPO 1 AL 6) MONTAJE AIRE ACONDICIONADO Y ACCESORIOS | D37: Sueldos (S/) | E37: 1.35 | F37: COSTO POR DIA | G37: COSTO POR HORA | H37: Tiempo trabajo (Hora) | I37: Dias de trabajo | J37: Costo trabajo (S/)
B38: Electricidad | C38: Operario | D38: 2400 | E38: =+D38*E37 -> 3240 | F38: =+E38/J4 -> 108 | G38: =+F38/J5 -> 13.5 | H38: - | I38: 3.5 | J38: =+I38*F38 -> 378
C39: Ayudante 1 | D39: 2000 | E39: =+D39*E37 -> 2700 | F39: =+E39/J4 -> 90 | G39: =+F39/J5 -> 11.25 | H39: - | I39: 3.5 | J39: =+I39*F39 -> 315
C40: Ayudante 2 | D40: 1600 | E40: =+D40*E37 -> 2160 | F40: =+E40/J4 -> 72 | G40: =+F40/J5 -> 9 | H40: - | I40: 3.5 | J40: =+I40*F40 -> 252
J41: =+SUM(J38:J40) -> 945
E43: Con beneficios | H43: POR 1 TABLERO AUTOSOPORTADO
B44: M. DE OBRA (TIPO 7 y 8) MONTAJE AIRE ACONDICIONADO Y ACCESORIOS | D44: Sueldos (S/) | E44: 1.35 | F44: COSTO POR DIA | G44: COSTO POR HORA | H44: Tiempo trabajo (Hora) | I44: Dias de trabajo | J44: Costo trabajo (S/)
B45: Electricidad | C45: Operario | D45: 2400 | E45: =+D45*E44 -> 3240 | F45: =+E45/J4 -> 108 | G45: =+F45/J5 -> 13.5 | H45: - | I45: 4.5 | J45: =+I45*F45 -> 486
C46: Ayudante 1 | D46: 2000 | E46: =+D46*E44 -> 2700 | F46: =+E46/J4 -> 90 | G46: =+F46/J5 -> 11.25 | H46: - | I46: 4.5 | J46: =+I46*F46 -> 405
C47: Ayudante 2 | D47: 1600 | E47: =+D47*E44 -> 2160 | F47: =+E47/J4 -> 72 | G47: =+F47/J5 -> 9 | H47: - | I47: 4.5 | J47: =+I47*F47 -> 324
J48: =+SUM(J45:J47) -> 1215
E50: Con beneficios | H50: POR 1 TABLERO AUTOSOPORTADO
B51: M. DE OBRA (TIPO 9 y 14) MONTAJE AIRE ACONDICIONADO Y ACCESORIOS | D51: Sueldos (S/) | E51: 1.35 | F51: COSTO POR DIA | G51: COSTO POR HORA | H51: Tiempo trabajo (Hora) | I51: Dias de trabajo | J51: Costo trabajo (S/)
B52: Electricidad | C52: Operario | D52: 2400 | E52: =+D52*E51 -> 3240 | F52: =+E52/J4 -> 108 | G52: =+F52/J5 -> 13.5 | H52: - | I52: 4 | J52: =+I52*F52 -> 432
C53: Ayudante 1 | D53: 2000 | E53: =+D53*E51 -> 2700 | F53: =+E53/J4 -> 90 | G53: =+F53/J5 -> 11.25 | H53: - | I53: 4 | J53: =+I53*F53 -> 360
C54: Ayudante 2 | D54: 1600 | E54: =+D54*E51 -> 2160 | F54: =+E54/J4 -> 72 | G54: =+F54/J5 -> 9 | H54: - | I54: 4 | J54: =+I54*F54 -> 288
J55: =+SUM(J52:J54) -> 1080
E57: Con beneficios | H57: POR 1 TABLERO AUTOSOPORTADO
B58: M. DE OBRA (TIPO 11, 12 y 13) MONTAJE AIRE ACONDICIONADO Y ACCESORIOS | D58: Sueldos (S/) | E58: 1.35 | F58: COSTO POR DIA | G58: COSTO POR HORA | H58: Tiempo trabajo (Hora) | I58: Dias de trabajo | J58: Costo trabajo (S/)
B59: Electricidad | C59: Operario | D59: 2400 | E59: =+D59*E58 -> 3240 | F59: =+E59/J4 -> 108 | G59: =+F59/J5 -> 13.5 | H59: - | I59: 4.5 | J59: =+I59*F59 -> 486
C60: Ayudante 1 | D60: 2000 | E60: =+D60*E58 -> 2700 | F60: =+E60/J4 -> 90 | G60: =+F60/J5 -> 11.25 | H60: - | I60: 4.5 | J60: =+I60*F60 -> 405
C61: Ayudante 2 | D61: 1600 | E61: =+D61*E58 -> 2160 | F61: =+E61/J4 -> 72 | G61: =+F61/J5 -> 9 | H61: - | I61: 4.5 | J61: =+I61*F61 -> 324
J62: =+SUM(J59:J61) -> 1215
B66: ADMINISTRATIVOS | C66: Sueldo (S/) | D66: Con beneficios 35%+ | E66: Costo por dia | F66: Costo por hora
B67: Gerencia | C67: 10000 | D67: =+C67*E10 -> 13500 | E67: =+D67/J4 -> 450 | F67: =+E67/J5 -> 56.25
B68: Jefatura Comercial | C68: 6000 | D68: =+C68*E10 -> 8100 | E68: =+D68/J4 -> 270 | F68: =+E68/J5 -> 33.75
B69: Asistente Licitaciones | C69: 3000 | D69: =+C69*E10 -> 4050 | E69: =+D69/J4 -> 135 | F69: =+E69/J5 -> 16.875
B70: Cotizador 1 | C70: 3000 | D70: =+C70*E10 -> 4050 | E70: =+D70/J4 -> 135 | F70: =+E70/J5 -> 16.875
B71: Cotizador 2 | C71: 3000 | D71: =+C71*E10 -> 4050 | E71: =+D71/J4 -> 135 | F71: =+E71/J5 -> 16.875
B72: Ingenieria | C72: 4000 | D72: =+C72*E10 -> 5400 | E72: =+D72/J4 -> 180 | F72: =+E72/J5 -> 22.5
B73: Dibujante | C73: 2000 | D73: =+C73*E10 -> 2700 | E73: =+D73/J4 -> 90 | F73: =+E73/J5 -> 11.25
B74: Logistico | C74: 2500 | D74: =+C74*E10 -> 3375 | E74: =+D74/J4 -> 112.5 | F74: =+E74/J5 -> 14.0625
B75: Finanzas | C75: 3000 | D75: =+C75*E10 -> 4050 | E75: =+D75/J4 -> 135 | F75: =+E75/J5 -> 16.875
B76: Contabilidad | C76: 2500 | D76: =+C76*E10 -> 3375 | E76: =+D76/J4 -> 112.5 | F76: =+E76/J5 -> 14.0625
B77: Vigilante | C77: 2000 | D77: =+C77*E10 -> 2700 | E77: =+D77/J4 -> 90 | F77: =+E77/J5 -> 11.25
C78: =+SUM(C67:C77) -> 41000 | D78: =+SUM(D67:D77) -> 55350 | E78: =+SUM(E67:E77) -> 1845 | F78: =+SUM(F67:F77) -> 230.625
B81: INFRAESTRUCTURA Y SERVICIOS | C81: Costo por mes | D81: Costo por dia | E81: Costo por hora
B82: Local | C82: 10000 | D82: =+C82/J4 -> 333.33333 | E82: =+D82/J5 -> 41.666667
B83: Servicio Electrico | C83: 4000 | D83: =+C83/J4 -> 133.33333 | E83: =+D83/J5 -> 16.666667
B84: Agua | C84: 1000 | D84: =+C84/J4 -> 33.333333 | E84: =+D84/J5 -> 4.1666667
B85: internet | C85: 500 | D85: =+C85/J4 -> 16.666667 | E85: =+D85/J5 -> 2.0833333
C86: =+SUM(C82:C85) -> 15500 | D86: =+SUM(D82:D85) -> 516.66667 | E86: =+SUM(E82:E85) -> 64.583333
B89: Costos M. Obra de Gabinetes Autosoportados | D89: Soles (S/) | G89: Costos M. Obra barras Autosoportado | J89: Soles (S/)
B90: M. Obra Gabinete 1800x800x450mm | D90: 860.58 | E90: 860.58 | G90: M. Obra Electricidad BUS BAR TIPO 1; 2; 3; 4; 4.1; 5; 7 | J90: 675
B91: M. Obra Gabinete 2000x800x450mm | D91: 959.58 | E91: 959.58 | G91: M. Obra Electricidad BUS BAR TIPO 6 | J91: 675
B92: M. Obra Gabinete 2100x800x600mm | D92: 1010.71 | G92: M. Obra Electricidad BUS BAR TIPO 8; 8.1 y 9.1 | J92: 675
B93: M. Obra Gabinete 2200x1000x700mm | D93: 1359.46 | G93: M. Obra Electricidad BUS BAR TIPO 9 | J93: 675
B94: M. Obra Gabinete 2200x1200x700mm | D94: 1557.46 | G94: M. Obra Electricidad BUS BAR TIPO 10; 10.1; 10.2; 11 | J94: 810
B95: M. Obra Gabinete 2400x1200x700mm | D95: =+J25+F78+E86 -> 1136.7083 | G95: M. Obra Electricidad BUS BAR TIPO 12 y 12.1 | J95: 810
G96: M. Obra Electricidad BUS BAR TIPO 14 (C01;G01), (C02;G01), (C01;G03), (C02;G03), (C03;G01), (C03;G03) | J96: 1215
G97: M. Obra Electricidad BUS BAR TIPO 13 y TIPO 14 (C01;G02), (C01;G04), (C02;G02), (C02;G04), (C03;G02), (C03;G04) | J97: 810
G98: M. Obra Electricidad Tablero Fotovoltaico AC | J98: 810

Sheet Cobre Autosoportado
B2: CALCULO DE COSTO BARRAS DE COBRE Y ACCESORIOS EN AUTOSOPORTADOS | I2: Tipo 1 | J2: Tipo 2 al 6 y 8 | K2: 7 | L2: 9, 9.1 y 10.1 | M2: 10 | N2: 11, 12, 12.1 y 13 | O2: 14 y 14.1 | P2: 15
I3: 250 | J3: 250 | K3: 500 | L3: 500 | M3: 750 | N3: 750 | O3: 1000 | P3: 1250
G4: T. Cambio | H4: 3.8 | I4: 160 | J4: 160 | K4: 80 | L4: 160 | M4: 160 | N4: 160 | O4: 160 | P4: 160
K5: 80 | L5: 160 | M5: 160 | N5: 160 | O5: 160 | P5: 160
N6: 160 | O6: 160
O7: 160
I8: =SUM(I3:I7) -> 410 | J8: =SUM(J3:J7) -> 410 | K8: =SUM(K3:K7) -> 660 | L8: =SUM(L3:L7) -> 820 | M8: =SUM(M3:M7) -> 1070 | N8: =SUM(N3:N7) -> 1230 | O8: =SUM(O3:O7) -> 1640 | P8: =SUM(P3:P7) -> 1570
B9: =+Hoja4!C7 -> COBRE BUS BAR TIPO 1; 2; 3; 4; 4.1; 5; 7
B10: ITEM | C10: DESCRIPCION | D10: BARRA DE CU | E10: CANTIDAD | F10: UNIDAD | G10: PRECIO (S/) | H10: SUB TOTAL (S/) | I10: A | J10: Largo | K10: Suples 1 | L10: Suples 2 | M10: Fases | N10: N° Barras | O10: Cant Interruptores
B11: 1 | C11: Cu Barras Colectoras 2P | D11: =+Barras!A17 -> 30 x 10 | E11: =SUM(J11:L11)*M11*N11*O11 -> 2 | F11: m | G11: =VLOOKUP(D11,Barras!$A$6:$T$31,20,0) -> 123.95 | H11: =+E11*G11 -> 247.9 | I11: =+Hoja4!L7 -> 497 | J11: 1 | K11: 0 | L11: 0 | M11: 2 | N11: 1 | O11: 1
B12: 2 | C12: Cu Derivaciones 2P (250A) Bateria | D12: =+Barras!A13 -> 25 x 3 | E12: =SUM(J12:L12)*M12*N12*O12 -> 0.7 | F12: m | G12: =VLOOKUP(D12,Barras!$A$6:$T$31,20,0) -> 31.45 | H12: =G12*E12 -> 22.015 | I12: 250 | J12: 0 | K12: 0.35 | L12: 0 | M12: 2 | N12: 1 | O12: 1
B13: 3 | C13: Cu Derivaciones 2P (160A) Controlador | D13: =+Barras!A8 -> 15 x 3 | E13: =SUM(J13:L13)*M13*N13*O13 -> 0.7 | F13: m | G13: =VLOOKUP(D13,Barras!$A$6:$T$31,20,0) -> 18.5 | H13: =+E13*G13 -> 12.95 | I13: 160 | J13: 0 | K13: 0.35 | L13: 0 | M13: 2 | N13: 1 | O13: 1
B14: 3 | C14: Cu Derivaciones 2P (63A) Inversor | D14: =+Barras!A8 -> 15 x 3 | E14: =SUM(J14:L14)*M14*N14*O14 -> 1.4 | F14: m | G14: =VLOOKUP(D14,Barras!$A$6:$T$31,20,0) -> 18.5 | H14: =+E14*G14 -> 25.9 | I14: 160 | J14: 0 | K14: 0.35 | L14: 0 | M14: 2 | N14: 1 | O14: 2
B15: 4 | C15: Cu Barra a tierra | D15: =+Barras!A16 -> 30 x 5 | E15: =SUM(J15:L15)*M15*N15*O15 -> 0.7 | F15: m | G15: =VLOOKUP(D15,Barras!$A$6:$T$31,20,0) -> 62.21 | H15: =+E15*G15 -> 43.547 | J15: 0.7 | K15: 0 | L15: 0 | M15: 1 | N15: 1 | O15: 1
B16: 5 | C16: Aisladores | D16: Cl 1/1000 | E16: 6 | F16: Pza | G16: =+Materiales!G88 -> 3.81 | H16: =+E16*G16 -> 22.86
B17: 6 | C17: Perneria | D17: Otros | E17: 1 | F17: Glb. | G17: 25 | H17: =G17*E17 -> 25
B18: 7 | C18: Placa de Fabricante | D18: 250x100mm | E18: 1 | F18: Pza | G18: 5.5 | H18: =+E18*G18 -> 5.5
B19: 8 | C19: Placa de Identificación Tablero | D19: 140x40mm | E19: 1 | F19: Pza | G19: 6 | H19: =+E19*G19 -> 6
B20: 9 | C20: Placa de Identificación Componentes | D20: 50x20mm | E20: 13 | F20: Pza | G20: 2 | H20: =+E20*G20 -> 26
B21: =+B9 -> COBRE BUS BAR TIPO 1; 2; 3; 4; 4.1; 5; 7 | H21: =SUM(H11:H20) -> 437.672 | I21: Soles
B24: =+Hoja4!C14 -> COBRE BUS BAR TIPO 6
B25: ITEM | C25: DESCRIPCION | D25: BARRA DE CU | E25: CANTIDAD | F25: UNIDAD | G25: PRECIO (S/) | H25: SUB TOTAL (S/) | I25: A | J25: Largo | K25: Suples 1 | L25: Suples 2 | M25: Fases | N25: N° Barras | O25: Cant Interruptores
B26: 1 | C26: Cu Barras Colectoras 2P | D26: =+Barras!A17 -> 30 x 10 | E26: =SUM(J26:L26)*M26*N26*O26 -> 2 | F26: m | G26: =VLOOKUP(D26,Barras!$A$6:$T$31,20,0) -> 123.95 | H26: =+E26*G26 -> 247.9 | I26: =+Hoja4!L14 -> 676 | J26: 1 | K26: 0 | L26: 0 | M26: 2 | N26: 1 | O26: 1
B27: 2 | C27: Cu Derivaciones 2P (250A) Bateria | D27: =+Barras!A13 -> 25 x 3 | E27: =SUM(J27:L27)*M27*N27*O27 -> 1.4 | F27: m | G27: =VLOOKUP(D27,Barras!$A$6:$T$31,20,0) -> 31.45 | H27: =G27*E27 -> 44.03 | I27: 250 | J27: 0 | K27: 0.35 | L27: 0 | M27: 2 | N27: 1 | O27: 2
B28: 3 | C28: Cu Derivaciones 2P (160A) Controlador | D28: =+Barras!A8 -> 15 x 3 | E28: =SUM(J28:L28)*M28*N28*O28 -> 0.7 | F28: m | G28: =VLOOKUP(D28,Barras!$A$6:$T$31,20,0) -> 18.5 | H28: =+E28*G28 -> 12.95 | I28: 160 | J28: 0 | K28: 0.35 | L28: 0 | M28: 2 | N28: 1 | O28: 1
B29: 3 | C29: Cu Derivaciones 2P (110A) Inversor | D29: =+Barras!A8 -> 15 x 3 | E29: =SUM(J29:L29)*M29*N29*O29 -> 1.4 | F29: m | G29: =VLOOKUP(D29,Barras!$A$6:$T$31,20,0) -> 18.5 | H29: =+E29*G29 -> 25.9 | I29: 160 | J29: 0 | K29: 0.35 | L29: 0 | M29: 2 | N29: 1 | O29: 2
B30: 4 | C30: Cu Barra a tierra | D30: =+Barras!A16 -> 30 x 5 | E30: =SUM(J30:L30)*M30*N30*O30 -> 0.7 | F30: m | G30: =VLOOKUP(D30,Barras!$A$6:$T$31,20,0) -> 62.21 | H30: =+E30*G30 -> 43.547 | J30: 0.7 | K30: 0 | L30: 0 | M30: 1 | N30: 1 | O30: 1
B31: 5 | C31: Aisladores | D31: Cl 1/1000 | E31: 6 | F31: Pza | G31: =+Materiales!G88 -> 3.81 | H31: =+E31*G31 -> 22.86
B32: 6 | C32: Perneria | D32: Otros | E32: 1 | F32: Glb. | G32: 25 | H32: =G32*E32 -> 25
B33: 7 | C33: Placa de Fabricante | D33: 250x100mm | E33: 1 | F33: Pza | G33: 5.5 | H33: =+E33*G33 -> 5.5
B34: 8 | C34: Placa de Identificación Tablero | D34: 140x40mm | E34: 1 | F34: Pza | G34: 6 | H34: =+E34*G34 -> 6
B35: 9 | C35: Placa de Identificación Componentes | D35: 50x20mm | E35: 13 | F35: Pza | G35: 2 | H35: =+E35*G35 -> 26
B36: =+B24 -> COBRE BUS BAR TIPO 6 | H36: =SUM(H26:H35) -> 459.687 | I36: Soles
B39: =+Hoja4!C15 -> COBRE BUS BAR TIPO 8; 8.1 y 9.1
B40: ITEM | C40: DESCRIPCION | D40: BARRA DE CU | E40: CANTIDAD | F40: UNIDAD | G40: PRECIO (S/) | H40: SUB TOTAL (S/) | I40: A | J40: Largo | K40: Suples 1 | L40: Suples 2 | M40: Fases | N40: N° Barras | O40: Cant Interruptores
B41: 1 | C41: Cu Barras Colectoras 2P | D41: =+Barras!A20 -> 40 x 10 | E41: =SUM(J41:L41)*M41*N41*O41 -> 2.8 | F41: m | G41: =VLOOKUP(D41,Barras!$A$6:$T$31,20,0) -> 165.73 | H41: =+E41*G41 -> 464.044 | I41: =+Hoja4!L15 -> 850 | J41: 1.4 | K41: 0 | L41: 0 | M41: 2 | N41: 1 | O41: 1
B42: 2 | C42: Cu Derivaciones 2P (250A) Bateria | D42: =+Barras!A13 -> 25 x 3 | E42: =SUM(J42:L42)*M42*N42*O42 -> 1.4 | F42: m | G42: =VLOOKUP(D42,Barras!$A$6:$T$31,20,0) -> 31.45 | H42: =G42*E42 -> 44.03 | I42: 250 | J42: 0 | K42: 0.35 | L42: 0 | M42: 2 | N42: 1 | O42: 2
B43: 3 | C43: Cu Derivaciones 2P (160A) Controlador | D43: =+Barras!A8 -> 15 x 3 | E43: =SUM(J43:L43)*M43*N43*O43 -> 1.4 | F43: m | G43: =VLOOKUP(D43,Barras!$A$6:$T$31,20,0) -> 18.5 | H43: =G43*E43 -> 25.9 | I43: 160 | J43: 0 | K43: 0.35 | L43: 0 | M43: 2 | N43: 1 | O43: 2
B44: 3 | C44: Cu Derivaciones 2P (110A) Inversor | D44: =+Barras!A8 -> 15 x 3 | E44: =SUM(J44:L44)*M44*N44*O44 -> 4.2 | F44: m | G44: =VLOOKUP(D44,Barras!$A$6:$T$31,20,0) -> 18.5 | H44: =+E44*G44 -> 77.7 | I44: 160 | J44: 0 | K44: 0.35 | L44: 0 | M44: 2 | N44: 1 | O44: 6
B45: 4 | C45: Cu Barra a tierra | D45: =+Barras!A16 -> 30 x 5 | E45: =SUM(J45:L45)*M45*N45*O45 -> 0.7 | F45: m | G45: =VLOOKUP(D45,Barras!$A$6:$T$31,20,0) -> 62.21 | H45: =+E45*G45 -> 43.547 | J45: 0.7 | K45: 0 | L45: 0 | M45: 1 | N45: 1 | O45: 1
B46: 5 | C46: Aisladores | D46: Cl 1/1000 | E46: 6 | F46: Pza | G46: =+Materiales!G88 -> 3.81 | H46: =+E46*G46 -> 22.86
B47: 6 | C47: Perneria | D47: Otros | E47: 1 | F47: Glb. | G47: 50 | H47: =G47*E47 -> 50
B48: 7 | C48: Placa de Fabricante | D48: 250x100mm | E48: 1 | F48: Pza | G48: 5.5 | H48: =+E48*G48 -> 5.5
B49: 8 | C49: Placa de Identificación Tablero | D49: 140x40mm | E49: 2 | F49: Pza | G49: 6 | H49: =+E49*G49 -> 12
B50: 9 | C50: Placa de Identificación Componentes | D50: 50x20mm | E50: 16 | F50: Pza | G50: 2 | H50: =+E50*G50 -> 32
B51: =+B39 -> COBRE BUS BAR TIPO 8; 8.1 y 9.1 | H51: =SUM(H41:H50) -> 777.581 | I51: Soles
B54: =+Hoja4!C18 -> COBRE BUS BAR TIPO 9
B55: ITEM | C55: DESCRIPCION | D55: BARRA DE CU | E55: CANTIDAD | F55: UNIDAD | G55: PRECIO (S/) | H55: SUB TOTAL (S/) | I55: A | J55: Largo | K55: Suples 1 | L55: Suples 2 | M55: Fases | N55: N° Barras | O55: Cant Interruptores
B56: 1 | C56: Cu Barras Colectoras 2P | D56: =+Barras!A24 -> 60 x 10 | E56: =SUM(J56:L56)*M56*N56*O56 -> 2.8 | F56: m | G56: =VLOOKUP(D56,Barras!$A$6:$T$31,20,0) -> 248.98 | H56: =G56*E56 -> 697.144 | I56: =+Hoja4!L18 -> 1180 | J56: 1.4 | K56: 0 | L56: 0 | M56: 2 | N56: 1 | O56: 1
B57: 2 | C57: Cu Derivaciones 2P (250A) Bateria | D57: =+Barras!A13 -> 25 x 3 | E57: =SUM(J57:L57)*M57*N57*O57 -> 2.1 | F57: m | G57: =VLOOKUP(D57,Barras!$A$6:$T$31,20,0) -> 31.45 | H57: =G57*E57 -> 66.045 | I57: 250 | J57: 0 | K57: 0.35 | L57: 0 | M57: 2 | N57: 1 | O57: 3
B58: 3 | C58: Cu Derivaciones 2P (160A) Controlador | D58: =+Barras!A8 -> 15 x 3 | E58: =SUM(J58:L58)*M58*N58*O58 -> 1.4 | F58: m | G58: =VLOOKUP(D58,Barras!$A$6:$T$31,20,0) -> 18.5 | H58: =G58*E58 -> 25.9 | I58: 160 | J58: 0 | K58: 0.35 | L58: 0 | M58: 2 | N58: 1 | O58: 2
B59: 3 | C59: Cu Derivaciones 2P (110A) Inversor | D59: =+Barras!A8 -> 15 x 3 | E59: =SUM(J59:L59)*M59*N59*O59 -> 4.2 | F59: m | G59: =VLOOKUP(D59,Barras!$A$6:$T$31,20,0) -> 18.5 | H59: =+E59*G59 -> 77.7 | I59: 160 | J59: 0 | K59: 0.35 | L59: 0 | M59: 2 | N59: 1 | O59: 6
B60: 4 | C60: Cu Barra a tierra | D60: =+Barras!A23 -> 60 x 5 | E60: =SUM(J60:L60)*M60*N60*O60 -> 0.7 | F60: m | G60: =VLOOKUP(D60,Barras!$A$6:$T$31,20,0) -> 123.48833 | H60: =+E60*G60 -> 86.441833 | J60: 0.7 | K60: 0 | L60: 0 | M60: 1 | N60: 1 | O60: 1
B61: 5 | C61: Aisladores | D61: Cl 1/1000 | E61: 8 | F61: Pza | G61: =+Materiales!G88 -> 3.81 | H61: =+E61*G61 -> 30.48
B62: 6 | C62: Perneria | D62: Otros | E62: 1 | F62: Glb. | G62: 50 | H62: =G62*E62 -> 50
B63: 7 | C63: Placa de Fabricante | D63: 250x100mm | E63: 1 | F63: Pza | G63: 5.5 | H63: =+E63*G63 -> 5.5
B64: 8 | C64: Placa de Identificación Tablero | D64: 140x40mm | E64: 2 | F64: Pza | G64: 6 | H64: =+E64*G64 -> 12
B65: 9 | C65: Placa de Identificación Componentes | D65: 50x20mm | E65: 16 | F65: Pza | G65: 2 | H65: =+E65*G65 -> 32
B66: =+B54 -> COBRE BUS BAR TIPO 9 | H66: =SUM(H56:H65) -> 1083.2108 | I66: Soles
B69: =+Hoja4!C19 -> COBRE BUS BAR TIPO 10; 10.1; 10.2; 11
B70: ITEM | C70: DESCRIPCION | D70: BARRA DE CU | E70: CANTIDAD | F70: UNIDAD | G70: PRECIO (S/) | H70: SUB TOTAL (S/) | I70: A | J70: Largo | K70: Suples 1 | L70: Suples 2 | M70: Fases | N70: N° Barras | O70: Cant Interruptores
B71: 1 | C71: Cu Barras Colectoras 2P | D71: =+Barras!A26 -> 80 x 10 | E71: =SUM(J71:L71)*M71*N71*O71 -> 2.8 | F71: m | G71: =VLOOKUP(D71,Barras!$A$6:$T$31,20,0) -> 329.535 | H71: =G71*E71 -> 922.698 | I71: =+Hoja4!L19 -> 1500 | J71: 1.4 | K71: 0 | L71: 0 | M71: 2 | N71: 1 | O71: 1
B72: 2 | C72: Cu Derivaciones 2P (250A) Bateria | D72: =+Barras!A13 -> 25 x 3 | E72: =SUM(J72:L72)*M72*N72*O72 -> 2.1 | F72: m | G72: =VLOOKUP(D72,Barras!$A$6:$T$31,20,0) -> 31.45 | H72: =G72*E72 -> 66.045 | I72: 250 | J72: 0 | K72: 0.35 | L72: 0 | M72: 2 | N72: 1 | O72: 3
B73: 3 | C73: Cu Derivaciones 2P (160A) Controlador | D73: =+Barras!A8 -> 15 x 3 | E73: =SUM(J73:L73)*M73*N73*O73 -> 2.1 | F73: m | G73: =VLOOKUP(D73,Barras!$A$6:$T$31,20,0) -> 18.5 | H73: =G73*E73 -> 38.85 | I73: 160 | J73: 0 | K73: 0.35 | L73: 0 | M73: 2 | N73: 1 | O73: 3
B74: 3 | C74: Cu Derivaciones 2P (110A) Inversor | D74: =+Barras!A8 -> 15 x 3 | E74: =SUM(J74:L74)*M74*N74*O74 -> 4.2 | F74: m | G74: =VLOOKUP(D74,Barras!$A$6:$T$31,20,0) -> 18.5 | H74: =+E74*G74 -> 77.7 | I74: 160 | J74: 0 | K74: 0.35 | L74: 0 | M74: 2 | N74: 1 | O74: 6
B75: 4 | C75: Cu Barra a tierra | D75: =+Barras!A20 -> 40 x 10 | E75: =SUM(J75:L75)*M75*N75*O75 -> 0.7 | F75: m | G75: =VLOOKUP(D75,Barras!$A$6:$T$31,20,0) -> 165.73 | H75: =+E75*G75 -> 116.011 | J75: 0.7 | K75: 0 | L75: 0 | M75: 1 | N75: 1 | O75: 1
B76: 5 | C76: Aisladores | D76: Cl 1/1000 | E76: 8 | F76: Pza | G76: =+Materiales!G88 -> 3.81 | H76: =+E76*G76 -> 30.48
B77: 6 | C77: Perneria | D77: Otros | E77: 1 | F77: Glb. | G77: 50 | H77: =G77*E77 -> 50
B78: 7 | C78: Placa de Fabricante | D78: 250x100mm | E78: 1 | F78: Pza | G78: 5.5 | H78: =+E78*G78 -> 5.5
B79: 8 | C79: Placa de Identificación Tablero | D79: 140x40mm | E79: 2 | F79: Pza | G79: 6 | H79: =+E79*G79 -> 12
B80: 9 | C80: Placa de Identificación Componentes | D80: 50x20mm | E80: 16 | F80: Pza | G80: 2 | H80: =+E80*G80 -> 32
B81: =+B69 -> COBRE BUS BAR TIPO 10; 10.1; 10.2; 11 | H81: =SUM(H71:H80) -> 1351.284 | I81: Soles
B84: =+Hoja4!C23 -> COBRE BUS BAR TIPO 12 y 12.1
B85: ITEM | C85: DESCRIPCION | D85: BARRA DE CU | E85: CANTIDAD | F85: UNIDAD | G85: PRECIO (S/) | H85: SUB TOTAL (S/) | I85: A | J85: Largo | K85: Suples 1 | L85: Suples 2 | M85: Fases | N85: N° Barras | O85: Cant Interruptores
B86: 1 | C86: Cu Barras Colectoras 2P | D86: =+Barras!A22 -> 50 x 10 | E86: =SUM(J86:L86)*M86*N86*O86 -> 5.6 | F86: m | G86: =VLOOKUP(D86,Barras!$A$6:$T$31,20,0) -> 206.20167 | H86: =G86*E86 -> 1154.7293 | I86: =+Hoja4!L23 -> 1720 | J86: 1.4 | K86: 0 | L86: 0 | M86: 2 | N86: 2 | O86: 1
B87: 2 | C87: Cu Derivaciones 2P (250A) Bateria | D87: =+Barras!A13 -> 25 x 3 | E87: =SUM(J87:L87)*M87*N87*O87 -> 2.8 | F87: m | G87: =VLOOKUP(D87,Barras!$A$6:$T$31,20,0) -> 31.45 | H87: =G87*E87 -> 88.06 | I87: 250 | J87: 0 | K87: 0.35 | L87: 0 | M87: 2 | N87: 1 | O87: 4
B88: 3 | C88: Cu Derivaciones 2P (160A) Controlador | D88: =+Barras!A8 -> 15 x 3 | E88: =SUM(J88:L88)*M88*N88*O88 -> 2.8 | F88: m | G88: =VLOOKUP(D88,Barras!$A$6:$T$31,20,0) -> 18.5 | H88: =G88*E88 -> 51.8 | I88: 160 | J88: 0 | K88: 0.35 | L88: 0 | M88: 2 | N88: 1 | O88: 4
B89: 3 | C89: Cu Derivaciones 2P (110A) Inversor | D89: =+Barras!A8 -> 15 x 3 | E89: =SUM(J89:L89)*M89*N89*O89 -> 4.2 | F89: m | G89: =VLOOKUP(D89,Barras!$A$6:$T$31,20,0) -> 18.5 | H89: =+E89*G89 -> 77.7 | I89: 160 | J89: 0 | K89: 0.35 | L89: 0 | M89: 2 | N89: 1 | O89: 6
B90: 4 | C90: Cu Barra a tierra | D90: =+Barras!A22 -> 50 x 10 | E90: =SUM(J90:L90)*M90*N90*O90 -> 0.7 | F90: m | G90: =VLOOKUP(D90,Barras!$A$6:$T$31,20,0) -> 206.20167 | H90: =+E90*G90 -> 144.34117 | J90: 0.7 | K90: 0 | L90: 0 | M90: 1 | N90: 1 | O90: 1
B91: 5 | C91: Aisladores | D91: Cl 1/1000 | E91: 8 | F91: Pza | G91: =+Materiales!G88 -> 3.81 | H91: =+E91*G91 -> 30.48
B92: 6 | C92: Perneria | D92: Otros | E92: 1 | F92: Glb. | G92: 50 | H92: =G92*E92 -> 50
B93: 7 | C93: Placa de Fabricante | D93: 250x100mm | E93: 1 | F93: Pza | G93: 5.5 | H93: =+E93*G93 -> 5.5
B94: 8 | C94: Placa de Identificación Tablero | D94: 140x40mm | E94: 2 | F94: Pza | G94: 6 | H94: =+E94*G94 -> 12
B95: 9 | C95: Placa de Identificación Componentes | D95: 50x20mm | E95: 16 | F95: Pza | G95: 2 | H95: =+E95*G95 -> 32
B96: =+B84 -> COBRE BUS BAR TIPO 12 y 12.1 | H96: =SUM(H86:H95) -> 1646.6105 | I96: Soles
B99: =+Hoja4!C25 -> COBRE BUS BAR TIPO 14 (C01;G01), (C02;G01), (C01;G03), (C02;G03), (C03;G01), (C03;G03)
B100: ITEM | C100: DESCRIPCION | D100: BARRA DE CU | E100: CANTIDAD | F100: UNIDAD | G100: PRECIO (S/) | H100: SUB TOTAL (S/) | I100: A | J100: Largo | K100: Suples 1 | L100: Suples 2 | M100: Fases | N100: N° Barras | O100: Cant Interruptores
B101: 1 | C101: Cu Barras Colectoras 2P | D101: =+Barras!A22 -> 50 x 10 | E101: =SUM(J101:L101)*M101*N101*O101 -> 3.2 | F101: m | G101: =VLOOKUP(D101,Barras!$A$6:$T$31,20,0) -> 206.20167 | H101: =G101*E101 -> 659.84533 | I101: =+Hoja4!L25 -> 1020 | J101: =1.6 -> 1.6 | K101: 0 | L101: 0 | M101: 2 | N101: 1 | O101: 1
B102: 2 | C102: Cu Derivaciones 2P (250A) Bateria | D102: =+Barras!A13 -> 25 x 3 | E102: =SUM(J102:L102)*M102*N102*O102 -> 2.8 | F102: m | G102: =VLOOKUP(D102,Barras!$A$6:$T$31,20,0) -> 31.45 | H102: =G102*E102 -> 88.06 | I102: 250 | J102: 0 | K102: 0.35 | L102: 0 | M102: 2 | N102: 1 | O102: 4
B103: 2 | C103: Cu Derivaciones 2P (320A) Inversor | D103: =+Barras!A14 -> 25 x 5 | E103: =SUM(J103:L103)*M103*N103*O103 -> 4.2 | F103: m | G103: =VLOOKUP(D103,Barras!$A$6:$T$31,20,0) -> 52.035 | H103: =G103*E103 -> 218.547 | I103: 320 | J103: 0 | K103: 0.35 | L103: 0 | M103: 2 | N103: 1 | O103: 6
B104: 3 | C104: Cu Barra a tierra | D104: =+Barras!A21 -> 50 x 5 | E104: =SUM(J104:L104)*M104*N104*O104 -> 0.35 | F104: m | G104: =VLOOKUP(D104,Barras!$A$6:$T$31,20,0) -> 104.06333 | H104: =+E104*G104 -> 36.422167 | J104: 0 | K104: 0.35 | L104: 0 | M104: 1 | N104: 1 | O104: 1
B105: 4 | C105: Aisladores | D105: Cl 1/1000 | E105: 8 | F105: Pza | G105: =+Materiales!G88 -> 3.81 | H105: =+E105*G105 -> 30.48
B106: 5 | C106: Perneria | D106: Otros | E106: 1 | F106: Glb. | G106: 50 | H106: =G106*E106 -> 50
B107: 6 | C107: Placa de Fabricante | D107: 250x100mm | E107: 1 | F107: Pza | G107: 5.5 | H107: =+E107*G107 -> 5.5
B108: 7 | C108: Placa de Identificación Tablero | D108: 140x40mm | E108: 2 | F108: Pza | G108: 6 | H108: =+E108*G108 -> 12
B109: 8 | C109: Placa de Identificación Componentes | D109: 50x20mm | E109: 16 | F109: Pza | G109: 2 | H109: =+E109*G109 -> 32
B110: =+B99 -> COBRE BUS BAR TIPO 14 (C01;G01), (C02;G01), (C01;G03), (C02;G03), (C03;G01), (C03;G03) | H110: =SUM(H101:H109) -> 1132.8545 | I110: Soles
B113: =+Hoja4!C31 -> COBRE BUS BAR TIPO 13 y TIPO 14 (C01;G02), (C01;G04), (C02;G02), (C02;G04), (C03;G02), (C03;G04)
B114: ITEM | C114: DESCRIPCION | D114: BARRA DE CU | E114: CANTIDAD | F114: UNIDAD | G114: PRECIO (S/) | H114: SUB TOTAL (S/) | I114: A | J114: Largo | K114: Suples 1 | L114: Suples 2 | M114: Fases | N114: N° Barras | O114: Cant Interruptores
B115: 1 | C115: Cu Barras Colectoras 2P | D115: =+Barras!A22 -> 50 x 10 | E115: =SUM(J115:L115)*M115*N115*O115 -> 6.4 | F115: m | G115: =VLOOKUP(D115,Barras!$A$6:$T$31,20,0) -> 206.20167 | H115: =G115*E115 -> 1319.6907 | I115: =+Hoja4!L31 -> 1720 | J115: =1.6 -> 1.6 | K115: 0 | L115: 0 | M115: 2 | N115: 2 | O115: 1
...

Sheet Hoja4
E6: BATERIA | F6: CONTROLADOR | J6: A | K6: BARRA | L6: CAPACIDAD
B7: 1 | C7: COBRE BUS BAR TIPO 1; 2; 3; 4; 4.1; 5; 7 | D7: tipo 1 | E7: 250 | F7: 160 | J7: =SUM(E7:I7) -> 410 | K7: =+Barras!A12 -> 20 x 10 | L7: =+Barras!D12 -> 497
D8: tipo 2 | E8: 250 | F8: 160
D9: tipo 3 | E9: 250 | F9: 160
D10: tipo 4 | E10: 250 | F10: 160
D11: tipo 4.1 | E11: 250 | F11: 160
D12: tipo 5 | E12: 250 | F12: 50 | G12: 50
D13: tipo 7 | E13: 250 | F13: 160
B14: 2 | C14: COBRE BUS BAR TIPO 6 | D14: tipo 6 | E14: 500 | F14: 80 | G14: 80 | J14: =SUM(E14:G14) -> 660 | K14: =+Barras!A17 -> 30 x 10 | L14: =+Barras!D17 -> 676
B15: 3 | C15: COBRE BUS BAR TIPO 8; 8.1 y 9.1 | D15: tipo 8 | E15: 500 | F15: 160 | G15: 160 | J15: =SUM(E15:G15) -> 820 | K15: =+Barras!A20 -> 40 x 10 | L15: =+Barras!D20 -> 850
D16: tipo 8.1 | E16: 500 | F16: 160 | G16: 160
D17: tipo 9.1 | E17: 500 | F17: 160 | G17: 160
B18: 4 | C18: COBRE BUS BAR TIPO 9 | D18: tipo 9 | E18: 750 | F18: 160 | G18: 160 | J18: =SUM(E18:I18) -> 1070 | K18: =+Barras!A24 -> 60 x 10 | L18: =+Barras!D24 -> 1180
B19: 5 | C19: COBRE BUS BAR TIPO 10; 10.1; 10.2; 11 | D19: tipo 10 | E19: 750 | F19: 160 | G19: 160 | H19: 160 | J19: =SUM(E19:H19) -> 1230 | K19: =+Barras!A26 -> 80 x 10 | L19: =+Barras!D26 -> 1500
D20: tipo 10.1 | E20: 750 | F20: 160 | G20: 160 | H20: 160
D21: tipo 10.2 | E21: 750 | F21: 160 | G21: 160 | H21: 160
D22: tipo 11 | E22: 750 | F22: 160 | G22: 160 | H22: 160
B23: 6 | C23: COBRE BUS BAR TIPO 12 y 12.1 | D23: tipo 12 | E23: 1000 | F23: 160 | G23: 160 | H23: 160 | I23: 160 | J23: =SUM(E23:I23) -> 1640 | K23: =+Barras!A22 -> 50 x 10 | L23: =+Barras!E22 -> 1720
D24: tipo 12.1 | E24: 1000 | F24: 160 | G24: 160 | H24: 160 | I24: 160 | K24: doble barra
B25: 7 | C25: COBRE BUS BAR TIPO 14 (C01;G01), (C02;G01), (C01;G03), (C02;G03), (C03;G01), (C03;G03) | D25: tipo 14 (C01;G01) | E25: 1000 | J25: =SUM(E30) -> 1000 | K25: =+Barras!A22 -> 50 x 10 | L25: =+Barras!D22 -> 1020
D26: tipo 14.(C02;G01) | E26: 1000
D27: tipo 14.(C01;G03) | E27: 1000
D28: tipo 14.(C02;G03) | E28: 1000
D29: tipo 14.(C03;G01) | E29: 1000
D30: tipo 14.(C03;G03) | E30: 1000
B31: 8 | C31: COBRE BUS BAR TIPO 13 y TIPO 14 (C01;G02), (C01;G04), (C02;G02), (C02;G04), (C03;G02), (C03;G04) | D31: tipo 13 | E31: 1250 | F31: 160 | G31: 160 | J31: =SUM(E31:G31) -> 1570 | L31: =+Barras!E22 -> 1720
D32: tipo 14 (C01;G02) | E32: 1250 | F32: 160 | G32: 160
D33: tipo 14.(C01;G04) | E33: 1250 | F33: 160 | G33: 160 | K33: =+Barras!A22 -> 50 x 10
D34: tipo 14.(C02;G02) | E34: 1250 | F34: 160 | G34: 160 | K34: doble barra
D35: tipo 14.(C02;G04) | E35: 1250 | F35: 160 | G35: 160
D36: tipo 14.(C03;G02) | E36: 1250 | F36: 160 | G36: 160
D37: tipo 14.(C03;G04) | E37: 1250 | F37: 160 | G37: 160

Sheet Barras
A1: Ancho x Espesor | B1: Área | C1: Peso (i) | D1: Corriente alterna hasta 60 Hz | L1: Corriente Continua y Alterna 16 2/3 Hz | T1: Precio
D2: Pintado | H2: Brillante | L2: Pintado | P2: Brillante
D3: Número de Barras | H3: Número de Barras | L3: Número de Barras | P3: Número de Barras
D4: 1 | E4: 2 | F4: 3 | G4: 4 | H4: 1 | I4: 2 | J4: 3 | K4: 4 | L4: 1 | M4: 2 | N4: 3 | O4: 4 | P4: 1 | Q4: 2 | R4: 3 | S4: 4
A5: mm | B5: mm2 | C5: kg/m
A6: 12 x 2 | B6: 23.5 | C6: 0.209 | D6: 123 | E6: 202 | F6: 228 | H6: 108 | I6: 182 | J6: 216 | L6: 123 | M6: 202 | N6: 233 | P6: 108 | Q6: 182 | R6: 220 | T6: =70.08/6 -> 11.68
A7: 15 x 2 | B7: 29.5 | C7: 0.262 | D7: 148 | E7: 240 | F7: 261 | H7: 128 | I7: 212 | J7: 247 | L7: 148 | M7: 240 | N7: 267 | P7: 128 | Q7: 212 | R7: 252
A8: 15 x 3 | B8: 44.5 | C8: 0.396 | D8: 187 | E8: 316 | F8: 381 | H8: 162 | I8: 282 | J8: 361 | L8: 187 | M8: 316 | N8: 387 | P8: 162 | Q8: 282 | R8: 365 | T8: =111/6 -> 18.5
A9: 20 x 2 | B9: 39.5 | C9: 0.351 | D9: 189 | E9: 302 | F9: 313 | H9: 162 | I9: 264 | J9: 298 | L9: 189 | M9: 302 | N9: 321 | P9: 162 | Q9: 266 | R9: 303
A10: 20 x 3 | B10: 59.5 | C10: 0.529 | D10: 237 | E10: 394 | F10: 454 | H10: 204 | I10: 348 | J10: 431 | L10: 237 | M10: 394 | N10: 463 | P10: 204 | Q10: 348 | R10: 437 | T10: =149.41/6 -> 24.901667
A11: 20 x 5 | B11: 99.1 | C11: 0.882 | D11: 319 | E11: 560 | F11: 728 | H11: 274 | I11: 500 | J11: 690 | L11: 320 | M11: 562 | N11: 729 | P11: 274 | Q11: 502 | R11: 687 | T11: =246.98/6 -> 41.163333
A12: 20 x 10 | B12: 199 | C12: 1.77 | D12: 497 | E12: 924 | F12: 1320 | H12: 427 | I12: 825 | J12: 1180 | L12: 499 | M12: 932 | N12: 1300 | P12: 428 | Q12: 832 | R12: 1210 | T12: =+T11*2 -> 82.326667
A13: 25 x 3 | B13: 74.5 | C13: 0.663 | D13: 287 | E13: 470 | F13: 525 | H13: 245 | I13: 412 | J13: 498 | L13: 287 | M13: 470 | N13: 536 | P13: 245 | Q13: 414 | R13: 506 | T13: =188.7/6 -> 31.45
A14: 25 x 5 | B14: 124 | C14: 1.11 | D14: 384 | E14: 662 | F14: 869 | H14: 327 | I14: 586 | J14: 795 | L14: 384 | M14: 664 | N14: 841 | P14: 327 | Q14: 590 | R14: 794 | T14: =312.21/6 -> 52.035
A15: 30 x 3 | B15: 89.5 | C15: 0.796 | D15: 337 | E15: 544 | F15: 593 | H15: 285 | I15: 476 | J15: 564 | L15: 337 | M15: 546 | N15: 608 | P15: 286 | Q15: 478 | R15: 575 | T15: =222/6 -> 37
A16: 30 x 5 | B16: 149 | C16: 1.33 | D16: 447 | E16: 760 | F16: 944 | H16: 379 | I16: 672 | J16: 896 | L16: 448 | M16: 766 | N16: 950 | P16: 380 | Q16: 676 | R16: 897 | T16: =373.26/6 -> 62.21 | U16: =+T16*2 -> 124.42
A17: 30 x 10 | B17: 299 | C17: 2.66 | D17: 676 | E17: 1200 | F17: 1670 | H17: 573 | I17: 1060 | J17: 1480 | L17: 683 | M17: 1230 | N17: 1630 | P17: 579 | Q17: 1080 | R17: 1520 | T17: =743.7/6 -> 123.95
A18: 40 x 3 | B18: 119 | C18: 1.06 | D18: 435 | E18: 692 | F18: 725 | H18: 366 | I18: 600 | J18: 690 | L18: 436 | M18: 696 | N18: 748 | P18: 367 | Q18: 604 | R18: 708 | T18: =298.7/6 -> 49.783333 | V18: =800*1.25 -> 1000
A19: 40 x 5 | B19: 199 | C19: 1.77 | D19: 573 | E19: 952 | F19: 1140 | H19: 482 | I19: 836 | J19: 1090 | L19: 576 | M19: 986 | N19: 1180 | P19: 484 | Q19: 848 | R19: 1100 | T19: =494.88/6 -> 82.48
A20: 40 x 10 | B20: 399 | C20: 3.55 | D20: 850 | E20: 1470 | F20: 2000 | G20: 2580 | H20: 715 | I20: 1290 | J20: 1770 | K20: 2280 | L20: 865 | M20: 1530 | N20: 2000 | P20: 728 | Q20: 1350 | R20: 1880 | T20: =994.38/6 -> 165.73
A21: 50 x 5 | B21: 249 | C21: 2.22 | D21: 697 | E21: 1140 | F21: 1330 | G21: 2010 | H21: 583 | I21: 994 | J21: 1260 | K21: 1920 | L21: 703 | M21: 1170 | N21: 1370 | P21: 588 | Q21: 1020 | R21: 1300 | T21: =624.38/6 -> 104.06333
A22: 50 x 10 | B22: 499 | C22: 4.44 | D22: 1020 | E22: 1720 | F22: 2320 | G22: 2950 | H22: 852 | I22: 1510 | J22: 2040 | K22: 2500 | L22: 1050 | M22: 1830 | N22: 2360 | P22: 875 | Q22: 1610 | R22: 2220 | T22: =1237.21/6 -> 206.20167
A23: 60 x 5 | B23: 299 | C23: 2.66 | D23: 826 | E23: 1330 | F23: 1510 | G23: 2310 | H23: 888 | I23: 1150 | J23: 1440 | K23: 2210 | L23: 836 | M23: 1370 | N23: 1580 | O23: 2080 | P23: 696 | Q23: 1190 | R23: 1500 | S23: 1970 | T23: =740.93/6 -> 123.48833
A24: 60 x 10 | B24: 599 | C24: 5.33 | D24: 1180 | E24: 1960 | F24: 2610 | G24: 3290 | H24: 985 | I24: 1720 | J24: 2300 | K24: 2900 | L24: 1230 | M24: 2130 | N24: 2720 | O24: 3580 | P24: 1020 | Q24: 1870 | R24: 2570 | S24: 3390 | T24: =1493.88/6 -> 248.98
A25: 80 x 5 | B25: 399 | C25: 3.55 | D25: 1070 | E25: 1880 | F25: 1830 | G25: 2830 | H25: 885 | I25: 1450 | J25: 1750 | K25: 2720 | L25: 1090 | M25: 1770 | N25: 1990 | O25: 2570 | P25: 902 | Q25: 1530 | R25: 1890 | S25: 2480 | T25: =631.3/6 -> 105.21667
A26: 80 x 10 | B26: 799 | C26: 7.11 | D26: 1500 | E26: 2410 | F26: 3170 | G26: 3930 | H26: 1240 | I26: 2110 | J26: 2790 | K26: 3450 | L26: 1590 | M26: 2730 | N26: 3420 | O26: 4490 | P26: 1310 | Q26: 2380 | R26: 3240 | S26: 4280 | T26: =1977.21/6 -> 329.535
A27: 100 x 5 | B27: 499 | C27: 4.44 | D27: 1300 | E27: 2010 | F27: 2150 | G27: 3300 | H27: 1080 | I27: 1730 | J27: 2050 | K27: 3190 | L27: 1340 | M27: 2160 | N27: 2380 | O27: 3080 | P27: 1110 | Q27: 1810 | R27: 2270 | S27: 2960
A28: 100 x 10 | B28: 999 | C28: 8.89 | D28: 1810 | E28: 2850 | F28: 3720 | G28: 4530 | H28: 1490 | I28: 2480 | J28: 3280 | K28: 3980 | L28: 1940 | M28: 3310 | N28: 4100 | O28: 5310 | P28: 1600 | Q28: 2890 | R28: 3900 | S28: 5150 | T28: =2474.38/6 -> 412.39667
A29: 120 x 10 | B29: 1200 | C29: 10.7 | D29: 2110 | E29: 3280 | F29: 4270 | G29: 5130 | H29: 1740 | I29: 2860 | J29: 3740 | K29: 4500 | L29: 2300 | M29: 3900 | N29: 4780 | O29: 6260 | P29: 1890 | Q29: 3390 | R29: 4580 | S29: 6010
A30: 160 x 10 | B30: 1600 | C30: 14.2 | D30: 2700 | E30: 4130 | F30: 5360 | G30: 6320 | H30: 2220 | I30: 3590 | J30: 4680 | K30: 5530 | L30: 3010 | M30: 5060 | N30: 6130 | O30: 8010 | P30: 2470 | Q30: 4400 | R30: 5860 | S30: 7110 | T30: =3718.5/6 -> 619.75
A31: 200 x 10 | B31: 2000 | C31: 17.8 | D31: 3290 | E31: 4970 | F31: 6430 | G31: 7490 | H31: 2690 | I31: 4310 | J31: 5610 | K31: 6540 | L31: 3720 | M31: 6220 | N31: 7480 | O31: 9730 | P31: 3040 | Q31: 5390 | R31: 7150 | S31: 9390

Sheet Hoja3
D6: bateria | E6: controlador
B7: COBRIZA | C7: tipo 1 | D7: 250 | E7: 160
C8: tipo 2 | D8: 250 | E8: 160
C9: tipo 3 | D9: 250 | E9: 160
C10: tipo 4 | D10: 250 | E10: 160
C11: tipo 4.1 | D11: 250 | E11: 160
C12: tipo 5 | D12: 250 | E12: 50 | F12: 50
C13: tipo 6 | D13: 500 | E13: 80 | F13: 80
C14: tipo 7 | D14: 250 | E14: 160
C15: tipo 8 | D15: 500 | E15: 160 | F15: 160
C16: tipo 8.1 | D16: 500 | E16: 160 | F16: 160
C17: tipo 9 | D17: 750 | E17: 160 | F17: 160
C18: tipo 9.1 | D18: 500 | E18: 160 | F18: 160
C19: tipo 10 | D19: 750 | E19: 160 | F19: 160 | G19: 160
C20: tipo 10.1 | D20: 750 | E20: 160 | F20: 160 | G20: 160
C21: tipo 10.2 | D21: 750 | E21: 160 | F21: 160 | G21: 160
C22: tipo 11 | D22: 750 | E22: 160 | F22: 160 | G22: 160
C23: tipo 12 | D23: 1000 | E23: 160 | F23: 160 | G23: 160 | H23: 160
C24: tipo 12.1 | D24: 1000 | E24: 160 | F24: 160 | G24: 160 | H24: 160
C25: tipo 13 | D25: 1250 | E25: 160 | F25: 160 | K25: 10X50
C26: tipo 14 (C01;G01) | D26: 1000 | K26: 10X50
C27: tipo 14 (C01;G02) | D27: 1250 | E27: 160 | F27: 160 | K27: 10X50
C28: tipo 14.(C01;G03) | D28: 1000
C29: tipo 14.(C01;G04) | D29: 1250 | E29: 160 | F29: 160
C30: tipo 14.(C02;G01) | D30: 1000
C31: tipo 14.(C02;G02) | D31: 1250 | E31: 160 | F31: 160
C32: tipo 14.(C02;G03) | D32: 1000
C33: tipo 14.(C02;G04) | D33: 1250 | E33: 160 | F33: 160
C34: tipo 14.(C03;G01) | D34: 1000
C35: tipo 14.(C03;G02) | D35: 1250 | E35: 160 | F35: 160
C36: tipo 14.(C03;G03) | D36: 1000
C37: tipo 14.(C03;G04) | D37: 1250 | E37: 160 | F37: 160
